[
  {
    "id": "ml2ey9",
    "url": "https://w.wallhaven.cc/full/ml/wallhaven-ml2ey9.png",
    "resolution": "3840x2160",
    "ratio": "1.78",
    "views": 7463,
    "favorites": 162,
    "colors": [
      "#000000",
      "#cccccc",
      "#424153",
      "#999999",
      "#ffffff"
    ],
    "tags": [],
    "source": "monthly_top"
  },
  {
    "id": "jevyrw",
    "url": "https://w.wallhaven.cc/full/je/wallhaven-jevyrw.png",
    "resolution": "1920x1080",
    "ratio": "1.78",
    "views": 5903,
    "favorites": 114,
    "colors": [
      "#424153",
      "#999999",
      "#cccccc",
      "#996633",
      "#66cccc"
    ],
    "tags": [],
    "source": "monthly_top"
  },
  {
    "id": "jevyyw",
    "url": "https://w.wallhaven.cc/full/je/wallhaven-jevyyw.jpg",
    "resolution": "3478x1956",
    "ratio": "1.78",
    "views": 5878,
    "favorites": 107,
    "colors": [
      "#424153",
      "#999999",
      "#663399",
      "#000000",
      "#333399"
    ],
    "tags": [],
    "source": "monthly_top"
  },
  {
    "id": "213op6",
    "url": "https://w.wallhaven.cc/full/21/wallhaven-213op6.jpg",
    "resolution": "2400x1350",
    "ratio": "1.78",
    "views": 4571,
    "favorites": 94,
    "colors": [
      "#424153",
      "#999999",
      "#333399",
      "#cccccc",
      "#abbcda"
    ],
    "tags": [],
    "source": "monthly_top"
  },
  {
    "id": "7jr7o9",
    "url": "https://w.wallhaven.cc/full/7j/wallhaven-7jr7o9.png",
    "resolution": "3840x2160",
    "ratio": "1.78",
    "views": 4079,
    "favorites": 31,
    "colors": [
      "#000000",
      "#424153",
      "#999999",
      "#663399",
      "#996633"
    ],
    "tags": [],
    "source": "monthly_top"
  },
  {
    "id": "xep3oo",
    "url": "https://w.wallhaven.cc/full/xe/wallhaven-xep3oo.png",
    "resolution": "1920x1080",
    "ratio": "1.78",
    "views": 4076,
    "favorites": 40,
    "colors": [
      "#000000",
      "#424153",
      "#336600",
      "#660000",
      "#ffcc33"
    ],
    "tags": [],
    "source": "monthly_top"
  },
  {
    "id": "1qr6mg",
    "url": "https://w.wallhaven.cc/full/1q/wallhaven-1qr6mg.png",
    "resolution": "3840x2160",
    "ratio": "1.78",
    "views": 4030,
    "favorites": 134,
    "colors": [
      "#333399",
      "#424153",
      "#000000",
      "#fdadc7",
      "#ea4c88"
    ],
    "tags": [],
    "source": "monthly_top"
  },
  {
    "id": "3qr2y9",
    "url": "https://w.wallhaven.cc/full/3q/wallhaven-3qr2y9.png",
    "resolution": "1920x1080",
    "ratio": "1.78",
    "views": 3999,
    "favorites": 59,
    "colors": [
      "#000000",
      "#424153",
      "#660000",
      "#cccccc",
      "#999999"
    ],
    "tags": [],
    "source": "monthly_top"
  },
  {
    "id": "og2wzm",
    "url": "https://w.wallhaven.cc/full/og/wallhaven-og2wzm.jpg",
    "resolution": "2238x1398",
    "ratio": "1.6",
    "views": 3759,
    "favorites": 100,
    "colors": [
      "#424153",
      "#cccccc",
      "#999999",
      "#ffffff",
      "#663399"
    ],
    "tags": [],
    "source": "monthly_top"
  },
  {
    "id": "9ory8k",
    "url": "https://w.wallhaven.cc/full/9o/wallhaven-9ory8k.jpg",
    "resolution": "3840x2160",
    "ratio": "1.78",
    "views": 3260,
    "favorites": 56,
    "colors": [
      "#ffffff",
      "#999999",
      "#cccccc",
      "#abbcda",
      "#424153"
    ],
    "tags": [],
    "source": "monthly_top"
  },
  {
    "id": "qrl855",
    "url": "https://w.wallhaven.cc/full/qr/wallhaven-qrl855.png",
    "resolution": "3840x2160",
    "ratio": "1.78",
    "views": 3203,
    "favorites": 45,
    "colors": [
      "#000000",
      "#660000",
      "#990000",
      "#424153",
      "#cc3333"
    ],
    "tags": [],
    "source": "monthly_top"
  },
  {
    "id": "vp53rm",
    "url": "https://w.wallhaven.cc/full/vp/wallhaven-vp53rm.png",
    "resolution": "3840x2160",
    "ratio": "1.78",
    "views": 3015,
    "favorites": 61,
    "colors": [
      "#333399",
      "#ffffff",
      "#424153",
      "#cccccc",
      "#999999"
    ],
    "tags": [],
    "source": "monthly_top"
  },
  {
    "id": "ly21ly",
    "url": "https://w.wallhaven.cc/full/ly/wallhaven-ly21ly.png",
    "resolution": "3840x2160",
    "ratio": "1.78",
    "views": 2984,
    "favorites": 79,
    "colors": [
      "#424153",
      "#000000",
      "#ffffff",
      "#999999",
      "#ffcc33"
    ],
    "tags": [],
    "source": "monthly_top"
  },
  {
    "id": "og2p6p",
    "url": "https://w.wallhaven.cc/full/og/wallhaven-og2p6p.png",
    "resolution": "3840x2160",
    "ratio": "1.78",
    "views": 2722,
    "favorites": 79,
    "colors": [
      "#424153",
      "#cccccc",
      "#000000",
      "#999999",
      "#abbcda"
    ],
    "tags": [],
    "source": "monthly_top"
  },
  {
    "id": "og28j9",
    "url": "https://w.wallhaven.cc/full/og/wallhaven-og28j9.png",
    "resolution": "4298x2417",
    "ratio": "1.78",
    "views": 2581,
    "favorites": 67,
    "colors": [
      "#424153",
      "#000000",
      "#999999",
      "#cccccc",
      "#abbcda"
    ],
    "tags": [],
    "source": "monthly_top"
  },
  {
    "id": "og2re5",
    "url": "https://w.wallhaven.cc/full/og/wallhaven-og2re5.jpg",
    "resolution": "8000x4488",
    "ratio": "1.78",
    "views": 2509,
    "favorites": 52,
    "colors": [
      "#424153",
      "#999999",
      "#000000",
      "#cccccc",
      "#abbcda"
    ],
    "tags": [],
    "source": "monthly_top"
  },
  {
    "id": "1qr2gw",
    "url": "https://w.wallhaven.cc/full/1q/wallhaven-1qr2gw.jpg",
    "resolution": "3840x2160",
    "ratio": "1.78",
    "views": 2346,
    "favorites": 63,
    "colors": [
      "#ffffff",
      "#cccccc",
      "#999999",
      "#424153",
      "#abbcda"
    ],
    "tags": [],
    "source": "monthly_top"
  },
  {
    "id": "e8w17o",
    "url": "https://w.wallhaven.cc/full/e8/wallhaven-e8w17o.png",
    "resolution": "2205x1240",
    "ratio": "1.78",
    "views": 2290,
    "favorites": 34,
    "colors": [
      "#333399",
      "#424153",
      "#ffffff",
      "#abbcda",
      "#000000"
    ],
    "tags": [],
    "source": "monthly_top"
  },
  {
    "id": "213mlm",
    "url": "https://w.wallhaven.cc/full/21/wallhaven-213mlm.png",
    "resolution": "5120x2880",
    "ratio": "1.78",
    "views": 2264,
    "favorites": 35,
    "colors": [
      "#ffcc33",
      "#cc6633",
      "#66cccc",
      "#996633",
      "#e7d8b1"
    ],
    "tags": [],
    "source": "monthly_top"
  },
  {
    "id": "gw2dgd",
    "url": "https://w.wallhaven.cc/full/gw/wallhaven-gw2dgd.jpg",
    "resolution": "4000x2250",
    "ratio": "1.78",
    "views": 2204,
    "favorites": 49,
    "colors": [
      "#424153",
      "#000000",
      "#999999",
      "#333399",
      "#663399"
    ],
    "tags": [],
    "source": "monthly_top"
  },
  {
    "id": "ml2y21",
    "url": "https://w.wallhaven.cc/full/ml/wallhaven-ml2y21.jpg",
    "resolution": "2048x1152",
    "ratio": "1.78",
    "views": 2073,
    "favorites": 35,
    "colors": [
      "#999999",
      "#e7d8b1",
      "#333399",
      "#cccc33",
      "#996633"
    ],
    "tags": [],
    "source": "monthly_top"
  },
  {
    "id": "e8w6ww",
    "url": "https://w.wallhaven.cc/full/e8/wallhaven-e8w6ww.jpg",
    "resolution": "2208x1242",
    "ratio": "1.78",
    "views": 2058,
    "favorites": 45,
    "colors": [
      "#999999",
      "#cccccc",
      "#ffffff",
      "#abbcda",
      "#424153"
    ],
    "tags": [],
    "source": "monthly_top"
  },
  {
    "id": "yqvp1x",
    "url": "https://w.wallhaven.cc/full/yq/wallhaven-yqvp1x.png",
    "resolution": "3840x2160",
    "ratio": "1.78",
    "views": 2057,
    "favorites": 66,
    "colors": [
      "#424153",
      "#000000",
      "#999999",
      "#ffcc33",
      "#abbcda"
    ],
    "tags": [],
    "source": "monthly_top"
  },
  {
    "id": "zp5r8y",
    "url": "https://w.wallhaven.cc/full/zp/wallhaven-zp5r8y.png",
    "resolution": "2560x1440",
    "ratio": "1.78",
    "views": 2033,
    "favorites": 43,
    "colors": [
      "#000000",
      "#999999",
      "#424153",
      "#cccccc",
      "#663300"
    ],
    "tags": [],
    "source": "monthly_top"
  },
  {
    "id": "x6p9w3",
    "url": "https://w.wallhaven.cc/full/x6/wallhaven-x6p9w3.png",
    "resolution": "1920x1080",
    "ratio": "1.78",
    "views": 2958,
    "favorites": 7,
    "colors": [
      "#424153",
      "#999999",
      "#abbcda",
      "#000000",
      "#333399"
    ],
    "tags": [],
    "source": "random_fill"
  },
  {
    "id": "e88j8l",
    "url": "https://w.wallhaven.cc/full/e8/wallhaven-e88j8l.png",
    "resolution": "2560x1440",
    "ratio": "1.78",
    "views": 2069,
    "favorites": 27,
    "colors": [
      "#ffcc33",
      "#996633",
      "#cc6633",
      "#ea4c88",
      "#424153"
    ],
    "tags": [],
    "source": "random_fill"
  },
  {
    "id": "9dgmox",
    "url": "https://w.wallhaven.cc/full/9d/wallhaven-9dgmox.png",
    "resolution": "1920x1080",
    "ratio": "1.78",
    "views": 1510,
    "favorites": 11,
    "colors": [
      "#cc0000",
      "#ffffff",
      "#fdadc7",
      "#cc3333",
      "#ea4c88"
    ],
    "tags": [],
    "source": "random_fill"
  },
  {
    "id": "4oqwwp",
    "url": "https://w.wallhaven.cc/full/4o/wallhaven-4oqwwp.jpg",
    "resolution": "1920x1080",
    "ratio": "1.78",
    "views": 5062,
    "favorites": 19,
    "colors": [
      "#ffffff",
      "#e7d8b1",
      "#999999",
      "#424153",
      "#cccccc"
    ],
    "tags": [],
    "source": "random_fill"
  },
  {
    "id": "28xe96",
    "url": "https://w.wallhaven.cc/full/28/wallhaven-28xe96.jpg",
    "resolution": "2100x1181",
    "ratio": "1.78",
    "views": 20171,
    "favorites": 208,
    "colors": [
      "#000000",
      "#424153",
      "#333399",
      "#999999",
      "#abbcda"
    ],
    "tags": [],
    "source": "random_fill"
  },
  {
    "id": "47159y",
    "url": "https://w.wallhaven.cc/full/47/wallhaven-47159y.png",
    "resolution": "1920x1080",
    "ratio": "1.78",
    "views": 4161,
    "favorites": 11,
    "colors": [
      "#fdadc7",
      "#ffffff",
      "#999999",
      "#424153",
      "#cccccc"
    ],
    "tags": [],
    "source": "random_fill"
  },
  {
    "id": "z8e3yj",
    "url": "https://w.wallhaven.cc/full/z8/wallhaven-z8e3yj.jpg",
    "resolution": "3840x2160",
    "ratio": "1.78",
    "views": 3489,
    "favorites": 20,
    "colors": [
      "#000000",
      "#424153",
      "#999999",
      "#336600",
      "#666600"
    ],
    "tags": [],
    "source": "random_fill"
  },
  {
    "id": "5gd9g7",
    "url": "https://w.wallhaven.cc/full/5g/wallhaven-5gd9g7.jpg",
    "resolution": "3840x2160",
    "ratio": "1.78",
    "views": 7776,
    "favorites": 91,
    "colors": [
      "#424153",
      "#000000",
      "#996633",
      "#663300",
      "#999999"
    ],
    "tags": [],
    "source": "random_fill"
  },
  {
    "id": "g72oqe",
    "url": "https://w.wallhaven.cc/full/g7/wallhaven-g72oqe.jpg",
    "resolution": "4096x2560",
    "ratio": "1.6",
    "views": 6971,
    "favorites": 119,
    "colors": [
      "#424153",
      "#999999",
      "#cccccc",
      "#660000",
      "#663300"
    ],
    "tags": [],
    "source": "random_fill"
  },
  {
    "id": "5yyxp8",
    "url": "https://w.wallhaven.cc/full/5y/wallhaven-5yyxp8.png",
    "resolution": "3840x2160",
    "ratio": "1.78",
    "views": 1364,
    "favorites": 17,
    "colors": [
      "#abbcda",
      "#ffffff",
      "#cccccc",
      "#424153",
      "#999999"
    ],
    "tags": [],
    "source": "random_fill"
  },
  {
    "id": "rrpvoq",
    "url": "https://w.wallhaven.cc/full/rr/wallhaven-rrpvoq.png",
    "resolution": "1920x1080",
    "ratio": "1.78",
    "views": 2822,
    "favorites": 15,
    "colors": [
      "#ffffff",
      "#ea4c88",
      "#fdadc7",
      "#996633",
      "#990000"
    ],
    "tags": [],
    "source": "random_fill"
  },
  {
    "id": "y88q1k",
    "url": "https://w.wallhaven.cc/full/y8/wallhaven-y88q1k.png",
    "resolution": "2560x1440",
    "ratio": "1.78",
    "views": 5365,
    "favorites": 69,
    "colors": [
      "#424153",
      "#999999",
      "#0099cc",
      "#66cccc",
      "#e7d8b1"
    ],
    "tags": [],
    "source": "random_fill"
  },
  {
    "id": "vmzw3l",
    "url": "https://w.wallhaven.cc/full/vm/wallhaven-vmzw3l.png",
    "resolution": "1920x1200",
    "ratio": "1.6",
    "views": 5338,
    "favorites": 17,
    "colors": [
      "#424153",
      "#999999",
      "#cccccc",
      "#000000",
      "#ffffff"
    ],
    "tags": [],
    "source": "random_fill"
  },
  {
    "id": "vmwvj8",
    "url": "https://w.wallhaven.cc/full/vm/wallhaven-vmwvj8.png",
    "resolution": "1920x1080",
    "ratio": "1.78",
    "views": 3146,
    "favorites": 25,
    "colors": [
      "#424153",
      "#996633",
      "#999999",
      "#000000",
      "#e7d8b1"
    ],
    "tags": [],
    "source": "random_fill"
  },
  {
    "id": "z8pkkv",
    "url": "https://w.wallhaven.cc/full/z8/wallhaven-z8pkkv.png",
    "resolution": "1920x1080",
    "ratio": "1.78",
    "views": 1949,
    "favorites": 16,
    "colors": [
      "#996633",
      "#663300",
      "#999999",
      "#000000",
      "#660000"
    ],
    "tags": [],
    "source": "random_fill"
  },
  {
    "id": "oxom7m",
    "url": "https://w.wallhaven.cc/full/ox/wallhaven-oxom7m.png",
    "resolution": "3840x2160",
    "ratio": "1.78",
    "views": 2987,
    "favorites": 11,
    "colors": [
      "#424153",
      "#999999",
      "#996633",
      "#cccccc",
      "#000000"
    ],
    "tags": [],
    "source": "random_fill"
  },
  {
    "id": "rdm11j",
    "url": "https://w.wallhaven.cc/full/rd/wallhaven-rdm11j.jpg",
    "resolution": "1920x1080",
    "ratio": "1.78",
    "views": 1482,
    "favorites": 7,
    "colors": [
      "#e7d8b1",
      "#999999",
      "#cc6633",
      "#ea4c88",
      "#fdadc7"
    ],
    "tags": [],
    "source": "random_fill"
  },
  {
    "id": "ogx1el",
    "url": "https://w.wallhaven.cc/full/og/wallhaven-ogx1el.jpg",
    "resolution": "3840x2160",
    "ratio": "1.78",
    "views": 1739,
    "favorites": 12,
    "colors": [
      "#424153",
      "#000000",
      "#999999",
      "#abbcda",
      "#663399"
    ],
    "tags": [],
    "source": "random_fill"
  },
  {
    "id": "0qm81r",
    "url": "https://w.wallhaven.cc/full/0q/wallhaven-0qm81r.jpg",
    "resolution": "1920x1080",
    "ratio": "1.78",
    "views": 4072,
    "favorites": 30,
    "colors": [
      "#ffffff",
      "#cccccc",
      "#abbcda",
      "#424153",
      "#999999"
    ],
    "tags": [],
    "source": "random_fill"
  },
  {
    "id": "lq7dqq",
    "url": "https://w.wallhaven.cc/full/lq/wallhaven-lq7dqq.png",
    "resolution": "3072x1728",
    "ratio": "1.78",
    "views": 3097,
    "favorites": 11,
    "colors": [
      "#333399",
      "#424153",
      "#0066cc",
      "#0099cc",
      "#ffffff"
    ],
    "tags": [],
    "source": "random_fill"
  },
  {
    "id": "eoe16w",
    "url": "https://w.wallhaven.cc/full/eo/wallhaven-eoe16w.jpg",
    "resolution": "1920x1200",
    "ratio": "1.6",
    "views": 2371,
    "favorites": 8,
    "colors": [
      "#999999",
      "#424153",
      "#000000",
      "#cccccc",
      "#996633"
    ],
    "tags": [],
    "source": "random_fill"
  },
  {
    "id": "4lzqwr",
    "url": "https://w.wallhaven.cc/full/4l/wallhaven-4lzqwr.jpg",
    "resolution": "1920x1080",
    "ratio": "1.78",
    "views": 3392,
    "favorites": 13,
    "colors": [
      "#ea4c88",
      "#999999",
      "#663300",
      "#996633",
      "#e7d8b1"
    ],
    "tags": [],
    "source": "random_fill"
  },
  {
    "id": "q61qdq",
    "url": "https://w.wallhaven.cc/full/q6/wallhaven-q61qdq.png",
    "resolution": "1920x1080",
    "ratio": "1.78",
    "views": 10186,
    "favorites": 40,
    "colors": [
      "#000000",
      "#990000",
      "#660000",
      "#cc3333",
      "#cc0000"
    ],
    "tags": [],
    "source": "random_fill"
  },
  {
    "id": "rq72vj",
    "url": "https://w.wallhaven.cc/full/rq/wallhaven-rq72vj.png",
    "resolution": "7680x4320",
    "ratio": "1.78",
    "views": 1095,
    "favorites": 5,
    "colors": [
      "#abbcda",
      "#66cccc",
      "#cccccc",
      "#999999",
      "#ffffff"
    ],
    "tags": [],
    "source": "random_fill"
  },
  {
    "id": "8x16p2",
    "url": "https://w.wallhaven.cc/full/8x/wallhaven-8x16p2.png",
    "resolution": "3840x2160",
    "ratio": "1.78",
    "views": 3995,
    "favorites": 14,
    "colors": [
      "#424153",
      "#000000",
      "#996633",
      "#663300",
      "#999999"
    ],
    "tags": [],
    "source": "random_fill"
  },
  {
    "id": "o5ml2m",
    "url": "https://w.wallhaven.cc/full/o5/wallhaven-o5ml2m.png",
    "resolution": "2560x1440",
    "ratio": "1.78",
    "views": 1469,
    "favorites": 2,
    "colors": [
      "#e7d8b1",
      "#ffffff",
      "#cccc33",
      "#fdadc7",
      "#999999"
    ],
    "tags": [],
    "source": "random_fill"
  },
  {
    "id": "lqkqxl",
    "url": "https://w.wallhaven.cc/full/lq/wallhaven-lqkqxl.png",
    "resolution": "1920x1080",
    "ratio": "1.78",
    "views": 3398,
    "favorites": 21,
    "colors": [
      "#fdadc7",
      "#e7d8b1",
      "#424153",
      "#999999",
      "#333399"
    ],
    "tags": [],
    "source": "random_fill"
  },
  {
    "id": "j5wymp",
    "url": "https://w.wallhaven.cc/full/j5/wallhaven-j5wymp.png",
    "resolution": "3840x2160",
    "ratio": "1.78",
    "views": 4314,
    "favorites": 26,
    "colors": [
      "#424153",
      "#ffffff",
      "#999999",
      "#996633",
      "#cccccc"
    ],
    "tags": [],
    "source": "random_fill"
  },
  {
    "id": "dg2jzg",
    "url": "https://w.wallhaven.cc/full/dg/wallhaven-dg2jzg.png",
    "resolution": "2560x1440",
    "ratio": "1.78",
    "views": 2935,
    "favorites": 17,
    "colors": [
      "#424153",
      "#000000",
      "#999999",
      "#996633",
      "#cccccc"
    ],
    "tags": [],
    "source": "random_fill"
  },
  {
    "id": "5g7977",
    "url": "https://w.wallhaven.cc/full/5g/wallhaven-5g7977.png",
    "resolution": "2048x1152",
    "ratio": "1.78",
    "views": 2521,
    "favorites": 20,
    "colors": [
      "#996633",
      "#e7d8b1",
      "#ffffff",
      "#000000",
      "#424153"
    ],
    "tags": [],
    "source": "random_fill"
  },
  {
    "id": "pk58qm",
    "url": "https://w.wallhaven.cc/full/pk/wallhaven-pk58qm.png",
    "resolution": "2080x1170",
    "ratio": "1.78",
    "views": 2834,
    "favorites": 23,
    "colors": [
      "#999999",
      "#424153",
      "#000000",
      "#663399",
      "#abbcda"
    ],
    "tags": [],
    "source": "random_fill"
  },
  {
    "id": "odevem",
    "url": "https://w.wallhaven.cc/full/od/wallhaven-odevem.png",
    "resolution": "3840x2160",
    "ratio": "1.78",
    "views": 4433,
    "favorites": 17,
    "colors": [
      "#424153",
      "#999999",
      "#e7d8b1",
      "#996633",
      "#000000"
    ],
    "tags": [],
    "source": "random_fill"
  },
  {
    "id": "6kel6q",
    "url": "https://w.wallhaven.cc/full/6k/wallhaven-6kel6q.png",
    "resolution": "1920x1080",
    "ratio": "1.78",
    "views": 5595,
    "favorites": 45,
    "colors": [
      "#000000",
      "#424153",
      "#999999",
      "#cccccc",
      "#ffffff"
    ],
    "tags": [],
    "source": "random_fill"
  },
  {
    "id": "yjvgzd",
    "url": "https://w.wallhaven.cc/full/yj/wallhaven-yjvgzd.jpg",
    "resolution": "2560x1600",
    "ratio": "1.6",
    "views": 6308,
    "favorites": 44,
    "colors": [
      "#333399",
      "#424153",
      "#999999",
      "#000000",
      "#663399"
    ],
    "tags": [],
    "source": "random_fill"
  },
  {
    "id": "pk7m29",
    "url": "https://w.wallhaven.cc/full/pk/wallhaven-pk7m29.png",
    "resolution": "3840x2160",
    "ratio": "1.78",
    "views": 11821,
    "favorites": 182,
    "colors": [
      "#424153",
      "#999999",
      "#cccccc",
      "#e7d8b1",
      "#996633"
    ],
    "tags": [],
    "source": "random_fill"
  },
  {
    "id": "m3m9pm",
    "url": "https://w.wallhaven.cc/full/m3/wallhaven-m3m9pm.png",
    "resolution": "3840x2160",
    "ratio": "1.78",
    "views": 2915,
    "favorites": 43,
    "colors": [
      "#000000",
      "#663300",
      "#424153",
      "#660000",
      "#996633"
    ],
    "tags": [],
    "source": "random_fill"
  },
  {
    "id": "425k6m",
    "url": "https://w.wallhaven.cc/full/42/wallhaven-425k6m.jpg",
    "resolution": "1920x1080",
    "ratio": "1.78",
    "views": 2334,
    "favorites": 4,
    "colors": [
      "#ffffff",
      "#e7d8b1",
      "#fdadc7",
      "#ea4c88",
      "#424153"
    ],
    "tags": [],
    "source": "random_fill"
  },
  {
    "id": "k97dj6",
    "url": "https://w.wallhaven.cc/full/k9/wallhaven-k97dj6.jpg",
    "resolution": "1920x1199",
    "ratio": "1.6",
    "views": 4403,
    "favorites": 48,
    "colors": [
      "#999999",
      "#424153",
      "#663399",
      "#663300",
      "#996633"
    ],
    "tags": [],
    "source": "random_fill"
  },
  {
    "id": "k9xxy1",
    "url": "https://w.wallhaven.cc/full/k9/wallhaven-k9xxy1.jpg",
    "resolution": "1920x1080",
    "ratio": "1.78",
    "views": 4290,
    "favorites": 18,
    "colors": [
      "#999999",
      "#424153",
      "#cccccc",
      "#000000",
      "#ffffff"
    ],
    "tags": [],
    "source": "random_fill"
  },
  {
    "id": "kxprwq",
    "url": "https://w.wallhaven.cc/full/kx/wallhaven-kxprwq.png",
    "resolution": "3840x2160",
    "ratio": "1.78",
    "views": 1858,
    "favorites": 13,
    "colors": [
      "#660000",
      "#000000",
      "#cc0000",
      "#990000",
      "#cc3333"
    ],
    "tags": [],
    "source": "random_fill"
  },
  {
    "id": "3lz969",
    "url": "https://w.wallhaven.cc/full/3l/wallhaven-3lz969.png",
    "resolution": "1920x1200",
    "ratio": "1.6",
    "views": 1302,
    "favorites": 7,
    "colors": [
      "#000000",
      "#cccccc",
      "#333399",
      "#424153",
      "#999999"
    ],
    "tags": [],
    "source": "random_fill"
  },
  {
    "id": "lm5y8p",
    "url": "https://w.wallhaven.cc/full/lm/wallhaven-lm5y8p.png",
    "resolution": "3840x2160",
    "ratio": "1.78",
    "views": 2040,
    "favorites": 10,
    "colors": [
      "#424153",
      "#999999",
      "#ea4c88",
      "#996633",
      "#000000"
    ],
    "tags": [],
    "source": "random_fill"
  },
  {
    "id": "nk6r1m",
    "url": "https://w.wallhaven.cc/full/nk/wallhaven-nk6r1m.jpg",
    "resolution": "1920x1080",
    "ratio": "1.78",
    "views": 6470,
    "favorites": 54,
    "colors": [
      "#000000",
      "#333399",
      "#0066cc",
      "#424153",
      "#660000"
    ],
    "tags": [],
    "source": "random_fill"
  },
  {
    "id": "573ow8",
    "url": "https://w.wallhaven.cc/full/57/wallhaven-573ow8.png",
    "resolution": "1920x1080",
    "ratio": "1.78",
    "views": 10447,
    "favorites": 161,
    "colors": [
      "#cccccc",
      "#999999",
      "#996633",
      "#e7d8b1",
      "#fdadc7"
    ],
    "tags": [],
    "source": "random_fill"
  },
  {
    "id": "3zlgrv",
    "url": "https://w.wallhaven.cc/full/3z/wallhaven-3zlgrv.jpg",
    "resolution": "1920x1080",
    "ratio": "1.78",
    "views": 2667,
    "favorites": 38,
    "colors": [
      "#ffffff",
      "#cccccc",
      "#abbcda",
      "#999999",
      "#424153"
    ],
    "tags": [],
    "source": "random_fill"
  },
  {
    "id": "q6zgl5",
    "url": "https://w.wallhaven.cc/full/q6/wallhaven-q6zgl5.png",
    "resolution": "1920x1080",
    "ratio": "1.78",
    "views": 2087,
    "favorites": 8,
    "colors": [
      "#ffffff",
      "#ea4c88",
      "#abbcda",
      "#cccccc",
      "#0066cc"
    ],
    "tags": [],
    "source": "random_fill"
  },
  {
    "id": "rrow61",
    "url": "https://w.wallhaven.cc/full/rr/wallhaven-rrow61.png",
    "resolution": "1920x1080",
    "ratio": "1.78",
    "views": 14713,
    "favorites": 142,
    "colors": [
      "#993399",
      "#663399",
      "#424153",
      "#333399",
      "#ea4c88"
    ],
    "tags": [],
    "source": "random_fill"
  },
  {
    "id": "zm9mzg",
    "url": "https://w.wallhaven.cc/full/zm/wallhaven-zm9mzg.jpg",
    "resolution": "5335x3000",
    "ratio": "1.78",
    "views": 10763,
    "favorites": 78,
    "colors": [
      "#424153",
      "#000000",
      "#999999",
      "#663300",
      "#660000"
    ],
    "tags": [],
    "source": "random_fill"
  },
  {
    "id": "4yk1jl",
    "url": "https://w.wallhaven.cc/full/4y/wallhaven-4yk1jl.jpg",
    "resolution": "1920x1080",
    "ratio": "1.78",
    "views": 4077,
    "favorites": 6,
    "colors": [
      "#ffffff",
      "#999999",
      "#424153",
      "#cccccc",
      "#000000"
    ],
    "tags": [],
    "source": "random_fill"
  },
  {
    "id": "zpopvw",
    "url": "https://w.wallhaven.cc/full/zp/wallhaven-zpopvw.jpg",
    "resolution": "1920x1080",
    "ratio": "1.78",
    "views": 978,
    "favorites": 4,
    "colors": [
      "#000000",
      "#424153",
      "#cccccc",
      "#ea4c88",
      "#663399"
    ],
    "tags": [],
    "source": "random_fill"
  },
  {
    "id": "o58zwl",
    "url": "https://w.wallhaven.cc/full/o5/wallhaven-o58zwl.png",
    "resolution": "1920x1080",
    "ratio": "1.78",
    "views": 1905,
    "favorites": 24,
    "colors": [
      "#999999",
      "#f5dd01",
      "#000000",
      "#990000",
      "#ffffff"
    ],
    "tags": [],
    "source": "random_fill"
  },
  {
    "id": "od52x9",
    "url": "https://w.wallhaven.cc/full/od/wallhaven-od52x9.jpg",
    "resolution": "1920x1200",
    "ratio": "1.6",
    "views": 2596,
    "favorites": 0,
    "colors": [
      "#ffffff",
      "#424153",
      "#e7d8b1",
      "#cccccc",
      "#999999"
    ],
    "tags": [],
    "source": "random_fill"
  },
  {
    "id": "eoogq8",
    "url": "https://w.wallhaven.cc/full/eo/wallhaven-eoogq8.png",
    "resolution": "1920x1080",
    "ratio": "1.78",
    "views": 4934,
    "favorites": 54,
    "colors": [
      "#424153",
      "#e7d8b1",
      "#000000",
      "#999999",
      "#996633"
    ],
    "tags": [],
    "source": "random_fill"
  },
  {
    "id": "yq8dy7",
    "url": "https://w.wallhaven.cc/full/yq/wallhaven-yq8dy7.jpg",
    "resolution": "2969x1670",
    "ratio": "1.78",
    "views": 1852,
    "favorites": 27,
    "colors": [
      "#66cccc",
      "#424153",
      "#663399",
      "#333399",
      "#000000"
    ],
    "tags": [],
    "source": "random_fill"
  },
  {
    "id": "8go5z2",
    "url": "https://w.wallhaven.cc/full/8g/wallhaven-8go5z2.png",
    "resolution": "1920x1080",
    "ratio": "1.78",
    "views": 1908,
    "favorites": 2,
    "colors": [
      "#ffffff",
      "#999999",
      "#e7d8b1",
      "#424153",
      "#fdadc7"
    ],
    "tags": [],
    "source": "random_fill"
  },
  {
    "id": "28yqey",
    "url": "https://w.wallhaven.cc/full/28/wallhaven-28yqey.png",
    "resolution": "3639x2047",
    "ratio": "1.78",
    "views": 5645,
    "favorites": 43,
    "colors": [
      "#ea4c88",
      "#fdadc7",
      "#424153",
      "#993399",
      "#000000"
    ],
    "tags": [],
    "source": "random_fill"
  },
  {
    "id": "0pz639",
    "url": "https://w.wallhaven.cc/full/0p/wallhaven-0pz639.jpg",
    "resolution": "1920x1200",
    "ratio": "1.6",
    "views": 2544,
    "favorites": 4,
    "colors": [
      "#ffffff",
      "#993399",
      "#999999",
      "#424153",
      "#663399"
    ],
    "tags": [],
    "source": "random_fill"
  },
  {
    "id": "49q510",
    "url": "https://w.wallhaven.cc/full/49/wallhaven-49q510.jpg",
    "resolution": "1920x1080",
    "ratio": "1.78",
    "views": 52978,
    "favorites": 180,
    "colors": [
      "#424153",
      "#000000",
      "#66cccc",
      "#0099cc",
      "#333399"
    ],
    "tags": [],
    "source": "random_fill"
  },
  {
    "id": "mdedey",
    "url": "https://w.wallhaven.cc/full/md/wallhaven-mdedey.jpg",
    "resolution": "2200x1238",
    "ratio": "1.78",
    "views": 2711,
    "favorites": 28,
    "colors": [
      "#ffffff",
      "#cccccc",
      "#333399",
      "#abbcda",
      "#0066cc"
    ],
    "tags": [],
    "source": "random_fill"
  },
  {
    "id": "yj1jyk",
    "url": "https://w.wallhaven.cc/full/yj/wallhaven-yj1jyk.png",
    "resolution": "1920x1080",
    "ratio": "1.78",
    "views": 4635,
    "favorites": 18,
    "colors": [
      "#ffffff",
      "#000000",
      "#663300",
      "#e7d8b1",
      "#424153"
    ],
    "tags": [],
    "source": "random_fill"
  },
  {
    "id": "nevd7o",
    "url": "https://w.wallhaven.cc/full/ne/wallhaven-nevd7o.jpg",
    "resolution": "1920x1080",
    "ratio": "1.78",
    "views": 2019,
    "favorites": 1,
    "colors": [
      "#999999",
      "#000000",
      "#fdadc7",
      "#e7d8b1",
      "#ea4c88"
    ],
    "tags": [],
    "source": "random_fill"
  },
  {
    "id": "v9lz68",
    "url": "https://w.wallhaven.cc/full/v9/wallhaven-v9lz68.jpg",
    "resolution": "2500x1406",
    "ratio": "1.78",
    "views": 1757,
    "favorites": 28,
    "colors": [
      "#424153",
      "#999999",
      "#e7d8b1",
      "#ffffff",
      "#000000"
    ],
    "tags": [],
    "source": "random_fill"
  },
  {
    "id": "zyw3xv",
    "url": "https://w.wallhaven.cc/full/zy/wallhaven-zyw3xv.png",
    "resolution": "2048x1150",
    "ratio": "1.78",
    "views": 5083,
    "favorites": 41,
    "colors": [],
    "tags": [],
    "source": "random_fill"
  },
  {
    "id": "956jy8",
    "url": "https://w.wallhaven.cc/full/95/wallhaven-956jy8.jpg",
    "resolution": "1920x1080",
    "ratio": "1.78",
    "views": 1907,
    "favorites": 6,
    "colors": [
      "#424153",
      "#000000",
      "#333399",
      "#999999",
      "#cccccc"
    ],
    "tags": [],
    "source": "random_fill"
  },
  {
    "id": "vmv213",
    "url": "https://w.wallhaven.cc/full/vm/wallhaven-vmv213.png",
    "resolution": "1920x1080",
    "ratio": "1.78",
    "views": 3818,
    "favorites": 14,
    "colors": [
      "#999999",
      "#424153",
      "#e7d8b1",
      "#ffffff",
      "#000000"
    ],
    "tags": [],
    "source": "random_fill"
  },
  {
    "id": "wq1ymq",
    "url": "https://w.wallhaven.cc/full/wq/wallhaven-wq1ymq.png",
    "resolution": "1920x1080",
    "ratio": "1.78",
    "views": 1507,
    "favorites": 6,
    "colors": [
      "#000000",
      "#424153",
      "#999999",
      "#e7d8b1",
      "#996633"
    ],
    "tags": [],
    "source": "random_fill"
  },
  {
    "id": "6oozzl",
    "url": "https://w.wallhaven.cc/full/6o/wallhaven-6oozzl.png",
    "resolution": "1920x1080",
    "ratio": "1.78",
    "views": 3107,
    "favorites": 10,
    "colors": [
      "#0066cc",
      "#ffffff",
      "#66cccc",
      "#abbcda",
      "#999999"
    ],
    "tags": [],
    "source": "random_fill"
  },
  {
    "id": "l3e3gq",
    "url": "https://w.wallhaven.cc/full/l3/wallhaven-l3e3gq.jpg",
    "resolution": "1920x1080",
    "ratio": "1.78",
    "views": 1038,
    "favorites": 5,
    "colors": [
      "#e7d8b1",
      "#fdadc7",
      "#cc6633",
      "#663300",
      "#ea4c88"
    ],
    "tags": [],
    "source": "random_fill"
  },
  {
    "id": "l8jd6r",
    "url": "https://w.wallhaven.cc/full/l8/wallhaven-l8jd6r.png",
    "resolution": "5760x3240",
    "ratio": "1.78",
    "views": 2166,
    "favorites": 50,
    "colors": [
      "#ffffff",
      "#424153",
      "#cccccc",
      "#999999",
      "#abbcda"
    ],
    "tags": [],
    "source": "random_fill"
  },
  {
    "id": "4xlk6l",
    "url": "https://w.wallhaven.cc/full/4x/wallhaven-4xlk6l.jpg",
    "resolution": "1920x1080",
    "ratio": "1.78",
    "views": 5465,
    "favorites": 14,
    "colors": [
      "#000000",
      "#424153",
      "#996633",
      "#ffffff",
      "#663300"
    ],
    "tags": [],
    "source": "random_fill"
  },
  {
    "id": "l3jv9p",
    "url": "https://w.wallhaven.cc/full/l3/wallhaven-l3jv9p.png",
    "resolution": "1920x1080",
    "ratio": "1.78",
    "views": 10372,
    "favorites": 40,
    "colors": [
      "#424153",
      "#999999",
      "#000000",
      "#cccccc",
      "#e7d8b1"
    ],
    "tags": [],
    "source": "random_fill"
  },
  {
    "id": "jxj9j5",
    "url": "https://w.wallhaven.cc/full/jx/wallhaven-jxj9j5.jpg",
    "resolution": "3840x2160",
    "ratio": "1.78",
    "views": 3169,
    "favorites": 28,
    "colors": [
      "#cccc33",
      "#999900",
      "#666600",
      "#996633",
      "#77cc33"
    ],
    "tags": [],
    "source": "random_fill"
  },
  {
    "id": "6ql8j7",
    "url": "https://w.wallhaven.cc/full/6q/wallhaven-6ql8j7.png",
    "resolution": "1920x1200",
    "ratio": "1.6",
    "views": 5058,
    "favorites": 20,
    "colors": [
      "#424153",
      "#000000",
      "#336600",
      "#999999",
      "#66cccc"
    ],
    "tags": [],
    "source": "random_fill"
  },
  {
    "id": "5gpvg8",
    "url": "https://w.wallhaven.cc/full/5g/wallhaven-5gpvg8.png",
    "resolution": "3070x1728",
    "ratio": "1.78",
    "views": 10443,
    "favorites": 76,
    "colors": [
      "#999999",
      "#424153",
      "#e7d8b1",
      "#77cc33",
      "#abbcda"
    ],
    "tags": [],
    "source": "random_fill"
  },
  {
    "id": "483l71",
    "url": "https://w.wallhaven.cc/full/48/wallhaven-483l71.jpg",
    "resolution": "1920x1200",
    "ratio": "1.6",
    "views": 5173,
    "favorites": 26,
    "colors": [
      "#000000",
      "#abbcda",
      "#ffffff",
      "#424153",
      "#66cccc"
    ],
    "tags": [],
    "source": "random_fill"
  },
  {
    "id": "76e8l3",
    "url": "https://w.wallhaven.cc/full/76/wallhaven-76e8l3.jpg",
    "resolution": "1920x1080",
    "ratio": "1.78",
    "views": 4001,
    "favorites": 23,
    "colors": [
      "#000000",
      "#424153",
      "#999999",
      "#996633",
      "#663300"
    ],
    "tags": [],
    "source": "random_fill"
  }
]