[
  {
    "id": "rqo8km",
    "url": "https://w.wallhaven.cc/full/rq/wallhaven-rqo8km.png",
    "resolution": "3840x2160",
    "ratio": "1.78",
    "views": 15075,
    "favorites": 140,
    "colors": [
      "#990000",
      "#000000",
      "#660000",
      "#663300",
      "#996633"
    ],
    "tags": [],
    "source": "monthly_top"
  },
  {
    "id": "6l2rk7",
    "url": "https://w.wallhaven.cc/full/6l/wallhaven-6l2rk7.jpg",
    "resolution": "3840x2160",
    "ratio": "1.78",
    "views": 8925,
    "favorites": 150,
    "colors": [
      "#424153",
      "#000000",
      "#333399",
      "#999999",
      "#996633"
    ],
    "tags": [],
    "source": "monthly_top"
  },
  {
    "id": "vpywgm",
    "url": "https://w.wallhaven.cc/full/vp/wallhaven-vpywgm.jpg",
    "resolution": "1920x1080",
    "ratio": "1.78",
    "views": 8442,
    "favorites": 63,
    "colors": [
      "#000000",
      "#999999",
      "#424153",
      "#cccccc",
      "#abbcda"
    ],
    "tags": [],
    "source": "monthly_top"
  },
  {
    "id": "jekg6w",
    "url": "https://w.wallhaven.cc/full/je/wallhaven-jekg6w.png",
    "resolution": "1920x1080",
    "ratio": "1.78",
    "views": 7074,
    "favorites": 122,
    "colors": [
      "#000000",
      "#ffffff",
      "#cccccc",
      "#424153",
      "#999999"
    ],
    "tags": [],
    "source": "monthly_top"
  },
  {
    "id": "yqgy2k",
    "url": "https://w.wallhaven.cc/full/yq/wallhaven-yqgy2k.png",
    "resolution": "2560x1440",
    "ratio": "1.78",
    "views": 5881,
    "favorites": 87,
    "colors": [
      "#000000",
      "#660000",
      "#990000",
      "#663300",
      "#cc0000"
    ],
    "tags": [],
    "source": "monthly_top"
  },
  {
    "id": "xejx2l",
    "url": "https://w.wallhaven.cc/full/xe/wallhaven-xejx2l.jpg",
    "resolution": "3840x2160",
    "ratio": "1.78",
    "views": 5754,
    "favorites": 127,
    "colors": [
      "#424153",
      "#999999",
      "#000000",
      "#ffffff",
      "#cccccc"
    ],
    "tags": [],
    "source": "monthly_top"
  },
  {
    "id": "e8wzkw",
    "url": "https://w.wallhaven.cc/full/e8/wallhaven-e8wzkw.png",
    "resolution": "1920x1080",
    "ratio": "1.78",
    "views": 5141,
    "favorites": 107,
    "colors": [
      "#424153",
      "#000000",
      "#996633",
      "#999999",
      "#663300"
    ],
    "tags": [],
    "source": "monthly_top"
  },
  {
    "id": "7jwz59",
    "url": "https://w.wallhaven.cc/full/7j/wallhaven-7jwz59.jpg",
    "resolution": "4800x2700",
    "ratio": "1.78",
    "views": 5001,
    "favorites": 87,
    "colors": [
      "#424153",
      "#77cc33",
      "#abbcda",
      "#cccccc",
      "#cccc33"
    ],
    "tags": [],
    "source": "monthly_top"
  },
  {
    "id": "7jwy3o",
    "url": "https://w.wallhaven.cc/full/7j/wallhaven-7jwy3o.jpg",
    "resolution": "1920x1080",
    "ratio": "1.78",
    "views": 4558,
    "favorites": 78,
    "colors": [
      "#ffffff",
      "#424153",
      "#999999",
      "#cccccc",
      "#000000"
    ],
    "tags": [],
    "source": "monthly_top"
  },
  {
    "id": "5ykvj9",
    "url": "https://w.wallhaven.cc/full/5y/wallhaven-5ykvj9.png",
    "resolution": "2560x1440",
    "ratio": "1.78",
    "views": 4461,
    "favorites": 95,
    "colors": [
      "#000000",
      "#333399",
      "#0066cc",
      "#ffffff",
      "#424153"
    ],
    "tags": [],
    "source": "monthly_top"
  },
  {
    "id": "gw9o8d",
    "url": "https://w.wallhaven.cc/full/gw/wallhaven-gw9o8d.jpg",
    "resolution": "1920x1080",
    "ratio": "1.78",
    "views": 3746,
    "favorites": 89,
    "colors": [
      "#e7d8b1",
      "#996633",
      "#424153",
      "#663300",
      "#999999"
    ],
    "tags": [],
    "source": "monthly_top"
  },
  {
    "id": "lyk5m2",
    "url": "https://w.wallhaven.cc/full/ly/wallhaven-lyk5m2.jpg",
    "resolution": "1920x1080",
    "ratio": "1.78",
    "views": 3711,
    "favorites": 67,
    "colors": [
      "#fdadc7",
      "#e7d8b1",
      "#996633",
      "#424153",
      "#000000"
    ],
    "tags": [],
    "source": "monthly_top"
  },
  {
    "id": "poj6x9",
    "url": "https://w.wallhaven.cc/full/po/wallhaven-poj6x9.jpg",
    "resolution": "4096x2304",
    "ratio": "1.78",
    "views": 3635,
    "favorites": 85,
    "colors": [
      "#424153",
      "#000000",
      "#999999",
      "#cccccc",
      "#ffffff"
    ],
    "tags": [],
    "source": "monthly_top"
  },
  {
    "id": "ly238y",
    "url": "https://w.wallhaven.cc/full/ly/wallhaven-ly238y.png",
    "resolution": "1920x1080",
    "ratio": "1.78",
    "views": 3574,
    "favorites": 65,
    "colors": [
      "#424153",
      "#66cccc",
      "#333399",
      "#0066cc",
      "#0099cc"
    ],
    "tags": [],
    "source": "monthly_top"
  },
  {
    "id": "9o8j2d",
    "url": "https://w.wallhaven.cc/full/9o/wallhaven-9o8j2d.png",
    "resolution": "3840x2160",
    "ratio": "1.78",
    "views": 3446,
    "favorites": 43,
    "colors": [
      "#000000",
      "#424153",
      "#660000",
      "#990000",
      "#999999"
    ],
    "tags": [],
    "source": "monthly_top"
  },
  {
    "id": "jekm5y",
    "url": "https://w.wallhaven.cc/full/je/wallhaven-jekm5y.jpg",
    "resolution": "1920x1080",
    "ratio": "1.78",
    "views": 3359,
    "favorites": 72,
    "colors": [
      "#ffffff",
      "#424153",
      "#cccccc",
      "#abbcda",
      "#e7d8b1"
    ],
    "tags": [],
    "source": "monthly_top"
  },
  {
    "id": "w5lpm6",
    "url": "https://w.wallhaven.cc/full/w5/wallhaven-w5lpm6.png",
    "resolution": "2560x1440",
    "ratio": "1.78",
    "views": 2981,
    "favorites": 51,
    "colors": [
      "#424153",
      "#333399",
      "#0066cc",
      "#000000",
      "#0099cc"
    ],
    "tags": [],
    "source": "monthly_top"
  },
  {
    "id": "oglzx7",
    "url": "https://w.wallhaven.cc/full/og/wallhaven-oglzx7.jpg",
    "resolution": "1920x1080",
    "ratio": "1.78",
    "views": 2983,
    "favorites": 50,
    "colors": [
      "#ffffff",
      "#424153",
      "#cccccc",
      "#999999",
      "#000000"
    ],
    "tags": [],
    "source": "monthly_top"
  },
  {
    "id": "ly2mzy",
    "url": "https://w.wallhaven.cc/full/ly/wallhaven-ly2mzy.jpg",
    "resolution": "4096x2304",
    "ratio": "1.78",
    "views": 2936,
    "favorites": 56,
    "colors": [
      "#999999",
      "#424153",
      "#cccccc",
      "#e7d8b1",
      "#ffffff"
    ],
    "tags": [],
    "source": "monthly_top"
  },
  {
    "id": "7jr6my",
    "url": "https://w.wallhaven.cc/full/7j/wallhaven-7jr6my.jpg",
    "resolution": "2100x1181",
    "ratio": "1.78",
    "views": 2864,
    "favorites": 49,
    "colors": [
      "#424153",
      "#999999",
      "#ffffff",
      "#cccccc",
      "#996633"
    ],
    "tags": [],
    "source": "monthly_top"
  },
  {
    "id": "xejr1o",
    "url": "https://w.wallhaven.cc/full/xe/wallhaven-xejr1o.png",
    "resolution": "3840x2160",
    "ratio": "1.78",
    "views": 2808,
    "favorites": 51,
    "colors": [
      "#ffffff",
      "#e7d8b1",
      "#424153",
      "#cccccc",
      "#999999"
    ],
    "tags": [],
    "source": "monthly_top"
  },
  {
    "id": "5yrdg7",
    "url": "https://w.wallhaven.cc/full/5y/wallhaven-5yrdg7.jpg",
    "resolution": "4096x2304",
    "ratio": "1.78",
    "views": 2732,
    "favorites": 74,
    "colors": [
      "#cccccc",
      "#999999",
      "#424153",
      "#ffffff",
      "#abbcda"
    ],
    "tags": [],
    "source": "monthly_top"
  },
  {
    "id": "e8egkr",
    "url": "https://w.wallhaven.cc/full/e8/wallhaven-e8egkr.jpg",
    "resolution": "5122x2879",
    "ratio": "1.78",
    "views": 2721,
    "favorites": 55,
    "colors": [
      "#424153",
      "#ffffff",
      "#999999",
      "#cccccc",
      "#996633"
    ],
    "tags": [],
    "source": "monthly_top"
  },
  {
    "id": "vpyw1l",
    "url": "https://w.wallhaven.cc/full/vp/wallhaven-vpyw1l.jpg",
    "resolution": "7000x3937",
    "ratio": "1.78",
    "views": 2613,
    "favorites": 38,
    "colors": [
      "#000000",
      "#424153",
      "#999999",
      "#abbcda",
      "#663399"
    ],
    "tags": [],
    "source": "monthly_top"
  },
  {
    "id": "dpzz6j",
    "url": "https://w.wallhaven.cc/full/dp/wallhaven-dpzz6j.png",
    "resolution": "5453x3067",
    "ratio": "1.78",
    "views": 4136,
    "favorites": 55,
    "colors": [
      "#424153",
      "#999999",
      "#996633",
      "#000000",
      "#ffffff"
    ],
    "tags": [],
    "source": "random_fill"
  },
  {
    "id": "k9rmw7",
    "url": "https://w.wallhaven.cc/full/k9/wallhaven-k9rmw7.png",
    "resolution": "1920x1080",
    "ratio": "1.78",
    "views": 2591,
    "favorites": 22,
    "colors": [
      "#ffffff",
      "#cccccc",
      "#999999",
      "#424153",
      "#abbcda"
    ],
    "tags": [],
    "source": "random_fill"
  },
  {
    "id": "neyp9o",
    "url": "https://w.wallhaven.cc/full/ne/wallhaven-neyp9o.jpg",
    "resolution": "1920x1080",
    "ratio": "1.78",
    "views": 4974,
    "favorites": 31,
    "colors": [
      "#424153",
      "#999999",
      "#000000",
      "#996633",
      "#663300"
    ],
    "tags": [],
    "source": "random_fill"
  },
  {
    "id": "3lqj5y",
    "url": "https://w.wallhaven.cc/full/3l/wallhaven-3lqj5y.png",
    "resolution": "1920x1080",
    "ratio": "1.78",
    "views": 3233,
    "favorites": 62,
    "colors": [
      "#000000",
      "#424153",
      "#663399",
      "#abbcda",
      "#999999"
    ],
    "tags": [],
    "source": "random_fill"
  },
  {
    "id": "42wqkx",
    "url": "https://w.wallhaven.cc/full/42/wallhaven-42wqkx.png",
    "resolution": "1920x1080",
    "ratio": "1.78",
    "views": 3025,
    "favorites": 14,
    "colors": [
      "#424153",
      "#996633",
      "#cc6633",
      "#999999",
      "#993399"
    ],
    "tags": [],
    "source": "random_fill"
  },
  {
    "id": "dpwvdl",
    "url": "https://w.wallhaven.cc/full/dp/wallhaven-dpwvdl.png",
    "resolution": "1920x1080",
    "ratio": "1.78",
    "views": 6571,
    "favorites": 90,
    "colors": [
      "#424153",
      "#000000",
      "#999999",
      "#e7d8b1",
      "#333399"
    ],
    "tags": [],
    "source": "random_fill"
  },
  {
    "id": "4xxg3l",
    "url": "https://w.wallhaven.cc/full/4x/wallhaven-4xxg3l.jpg",
    "resolution": "1920x1080",
    "ratio": "1.78",
    "views": 5161,
    "favorites": 27,
    "colors": [
      "#999999",
      "#abbcda",
      "#424153",
      "#0066cc",
      "#66cccc"
    ],
    "tags": [],
    "source": "random_fill"
  },
  {
    "id": "x11ewo",
    "url": "https://w.wallhaven.cc/full/x1/wallhaven-x11ewo.jpg",
    "resolution": "1920x1200",
    "ratio": "1.6",
    "views": 2981,
    "favorites": 1,
    "colors": [
      "#000000",
      "#663300",
      "#660000",
      "#996633",
      "#999999"
    ],
    "tags": [],
    "source": "random_fill"
  },
  {
    "id": "3k5kgy",
    "url": "https://w.wallhaven.cc/full/3k/wallhaven-3k5kgy.jpg",
    "resolution": "1920x1080",
    "ratio": "1.78",
    "views": 3414,
    "favorites": 14,
    "colors": [
      "#abbcda",
      "#cccccc",
      "#66cccc",
      "#ffffff",
      "#999999"
    ],
    "tags": [],
    "source": "random_fill"
  },
  {
    "id": "7p998y",
    "url": "https://w.wallhaven.cc/full/7p/wallhaven-7p998y.jpg",
    "resolution": "1920x1080",
    "ratio": "1.78",
    "views": 2752,
    "favorites": 43,
    "colors": [
      "#ffffff",
      "#cccccc",
      "#abbcda",
      "#66cccc",
      "#999999"
    ],
    "tags": [],
    "source": "random_fill"
  },
  {
    "id": "219vxm",
    "url": "https://w.wallhaven.cc/full/21/wallhaven-219vxm.png",
    "resolution": "1920x1080",
    "ratio": "1.78",
    "views": 910,
    "favorites": 26,
    "colors": [
      "#424153",
      "#663399",
      "#fdadc7",
      "#996633",
      "#abbcda"
    ],
    "tags": [],
    "source": "random_fill"
  },
  {
    "id": "yjregk",
    "url": "https://w.wallhaven.cc/full/yj/wallhaven-yjregk.jpg",
    "resolution": "1920x1080",
    "ratio": "1.78",
    "views": 2979,
    "favorites": 8,
    "colors": [
      "#663300",
      "#996633",
      "#666600",
      "#660000",
      "#cc6633"
    ],
    "tags": [],
    "source": "random_fill"
  },
  {
    "id": "nmmv79",
    "url": "https://w.wallhaven.cc/full/nm/wallhaven-nmmv79.jpg",
    "resolution": "1920x1200",
    "ratio": "1.6",
    "views": 5952,
    "favorites": 40,
    "colors": [
      "#000000",
      "#660000",
      "#424153",
      "#990000",
      "#cc0000"
    ],
    "tags": [],
    "source": "random_fill"
  },
  {
    "id": "g79g8l",
    "url": "https://w.wallhaven.cc/full/g7/wallhaven-g79g8l.png",
    "resolution": "1920x1080",
    "ratio": "1.78",
    "views": 1399,
    "favorites": 2,
    "colors": [
      "#ffffff",
      "#999999",
      "#424153",
      "#abbcda",
      "#cc3333"
    ],
    "tags": [],
    "source": "random_fill"
  },
  {
    "id": "d8gqqm",
    "url": "https://w.wallhaven.cc/full/d8/wallhaven-d8gqqm.jpg",
    "resolution": "3676x2066",
    "ratio": "1.78",
    "views": 1147,
    "favorites": 7,
    "colors": [
      "#999999",
      "#cccccc",
      "#ffffff",
      "#424153",
      "#000000"
    ],
    "tags": [],
    "source": "random_fill"
  },
  {
    "id": "2kqvv6",
    "url": "https://w.wallhaven.cc/full/2k/wallhaven-2kqvv6.jpg",
    "resolution": "2000x1125",
    "ratio": "1.78",
    "views": 3908,
    "favorites": 25,
    "colors": [
      "#424153",
      "#000000",
      "#999999",
      "#cccccc",
      "#ffffff"
    ],
    "tags": [],
    "source": "random_fill"
  },
  {
    "id": "vqgj88",
    "url": "https://w.wallhaven.cc/full/vq/wallhaven-vqgj88.jpg",
    "resolution": "1920x1080",
    "ratio": "1.78",
    "views": 1156,
    "favorites": 6,
    "colors": [
      "#cccccc",
      "#424153",
      "#999999",
      "#996633",
      "#abbcda"
    ],
    "tags": [],
    "source": "random_fill"
  },
  {
    "id": "mplxy8",
    "url": "https://w.wallhaven.cc/full/mp/wallhaven-mplxy8.png",
    "resolution": "1920x1080",
    "ratio": "1.78",
    "views": 2114,
    "favorites": 6,
    "colors": [
      "#ea4c88",
      "#ffffff",
      "#cc6633",
      "#424153",
      "#e7d8b1"
    ],
    "tags": [],
    "source": "random_fill"
  },
  {
    "id": "v9er85",
    "url": "https://w.wallhaven.cc/full/v9/wallhaven-v9er85.png",
    "resolution": "1920x1080",
    "ratio": "1.78",
    "views": 1857,
    "favorites": 5,
    "colors": [
      "#999999",
      "#424153",
      "#cccccc",
      "#993399",
      "#663399"
    ],
    "tags": [],
    "source": "random_fill"
  },
  {
    "id": "85ov3y",
    "url": "https://w.wallhaven.cc/full/85/wallhaven-85ov3y.jpg",
    "resolution": "3410x1918",
    "ratio": "1.78",
    "views": 3593,
    "favorites": 39,
    "colors": [
      "#ffffff",
      "#cccccc",
      "#999999",
      "#996633",
      "#424153"
    ],
    "tags": [],
    "source": "random_fill"
  },
  {
    "id": "gjqlgd",
    "url": "https://w.wallhaven.cc/full/gj/wallhaven-gjqlgd.png",
    "resolution": "1920x1080",
    "ratio": "1.78",
    "views": 2960,
    "favorites": 15,
    "colors": [
      "#424153",
      "#996633",
      "#999999",
      "#ffffff",
      "#000000"
    ],
    "tags": [],
    "source": "random_fill"
  },
  {
    "id": "mpgzv8",
    "url": "https://w.wallhaven.cc/full/mp/wallhaven-mpgzv8.jpg",
    "resolution": "1920x1080",
    "ratio": "1.78",
    "views": 2481,
    "favorites": 7,
    "colors": [
      "#000000",
      "#424153",
      "#e7d8b1",
      "#996633",
      "#663300"
    ],
    "tags": [],
    "source": "random_fill"
  },
  {
    "id": "kw3kvq",
    "url": "https://w.wallhaven.cc/full/kw/wallhaven-kw3kvq.png",
    "resolution": "2880x1800",
    "ratio": "1.6",
    "views": 2298,
    "favorites": 11,
    "colors": [
      "#abbcda",
      "#663399",
      "#999999",
      "#424153",
      "#e7d8b1"
    ],
    "tags": [],
    "source": "random_fill"
  },
  {
    "id": "exwpll",
    "url": "https://w.wallhaven.cc/full/ex/wallhaven-exwpll.jpg",
    "resolution": "7524x4700",
    "ratio": "1.6",
    "views": 5256,
    "favorites": 55,
    "colors": [
      "#999999",
      "#cccccc",
      "#ffffff",
      "#424153",
      "#e7d8b1"
    ],
    "tags": [],
    "source": "random_fill"
  },
  {
    "id": "l83mjy",
    "url": "https://w.wallhaven.cc/full/l8/wallhaven-l83mjy.png",
    "resolution": "1920x1200",
    "ratio": "1.6",
    "views": 1910,
    "favorites": 13,
    "colors": [
      "#000000",
      "#424153",
      "#999999",
      "#cccccc",
      "#e7d8b1"
    ],
    "tags": [],
    "source": "random_fill"
  },
  {
    "id": "l3kvpy",
    "url": "https://w.wallhaven.cc/full/l3/wallhaven-l3kvpy.png",
    "resolution": "2560x1440",
    "ratio": "1.78",
    "views": 3988,
    "favorites": 54,
    "colors": [
      "#ffffff",
      "#663300",
      "#996633",
      "#e7d8b1",
      "#424153"
    ],
    "tags": [],
    "source": "random_fill"
  },
  {
    "id": "eolx1w",
    "url": "https://w.wallhaven.cc/full/eo/wallhaven-eolx1w.jpg",
    "resolution": "3840x2160",
    "ratio": "1.78",
    "views": 7968,
    "favorites": 16,
    "colors": [
      "#000000",
      "#e7d8b1",
      "#663300",
      "#996633",
      "#cc6633"
    ],
    "tags": [],
    "source": "random_fill"
  },
  {
    "id": "y8j8lg",
    "url": "https://w.wallhaven.cc/full/y8/wallhaven-y8j8lg.jpg",
    "resolution": "1920x1080",
    "ratio": "1.78",
    "views": 4428,
    "favorites": 32,
    "colors": [
      "#424153",
      "#333399",
      "#000000",
      "#663399",
      "#999999"
    ],
    "tags": [],
    "source": "random_fill"
  },
  {
    "id": "8xvpey",
    "url": "https://w.wallhaven.cc/full/8x/wallhaven-8xvpey.jpg",
    "resolution": "2560x1600",
    "ratio": "1.6",
    "views": 3218,
    "favorites": 6,
    "colors": [
      "#000000",
      "#660000",
      "#663300",
      "#999999",
      "#424153"
    ],
    "tags": [],
    "source": "random_fill"
  },
  {
    "id": "ymkpv7",
    "url": "https://w.wallhaven.cc/full/ym/wallhaven-ymkpv7.jpg",
    "resolution": "3840x2160",
    "ratio": "1.78",
    "views": 9775,
    "favorites": 52,
    "colors": [
      "#cccccc",
      "#424153",
      "#999999",
      "#000000",
      "#ffffff"
    ],
    "tags": [],
    "source": "random_fill"
  },
  {
    "id": "ympdmd",
    "url": "https://w.wallhaven.cc/full/ym/wallhaven-ympdmd.png",
    "resolution": "2012x1132",
    "ratio": "1.78",
    "views": 1797,
    "favorites": 12,
    "colors": [
      "#ea4c88",
      "#996633",
      "#ffffff",
      "#999999",
      "#cccccc"
    ],
    "tags": [],
    "source": "random_fill"
  },
  {
    "id": "neork0",
    "url": "https://w.wallhaven.cc/full/ne/wallhaven-neork0.jpg",
    "resolution": "1920x1080",
    "ratio": "1.78",
    "views": 45219,
    "favorites": 143,
    "colors": [
      "#424153",
      "#999999",
      "#000000",
      "#ffffff",
      "#e7d8b1"
    ],
    "tags": [],
    "source": "random_fill"
  },
  {
    "id": "eo916w",
    "url": "https://w.wallhaven.cc/full/eo/wallhaven-eo916w.jpg",
    "resolution": "1920x1080",
    "ratio": "1.78",
    "views": 1896,
    "favorites": 6,
    "colors": [
      "#000000",
      "#e7d8b1",
      "#999999",
      "#fdadc7",
      "#ffffff"
    ],
    "tags": [],
    "source": "random_fill"
  },
  {
    "id": "nmz11y",
    "url": "https://w.wallhaven.cc/full/nm/wallhaven-nmz11y.jpg",
    "resolution": "2000x1125",
    "ratio": "1.78",
    "views": 5503,
    "favorites": 29,
    "colors": [
      "#999999",
      "#424153",
      "#663399",
      "#66cccc",
      "#abbcda"
    ],
    "tags": [],
    "source": "random_fill"
  },
  {
    "id": "odjjx5",
    "url": "https://w.wallhaven.cc/full/od/wallhaven-odjjx5.jpg",
    "resolution": "1920x1200",
    "ratio": "1.6",
    "views": 1863,
    "favorites": 1,
    "colors": [
      "#e7d8b1",
      "#ffffff",
      "#999999",
      "#cccccc",
      "#cccc33"
    ],
    "tags": [],
    "source": "random_fill"
  },
  {
    "id": "4dr2ll",
    "url": "https://w.wallhaven.cc/full/4d/wallhaven-4dr2ll.png",
    "resolution": "3840x2160",
    "ratio": "1.78",
    "views": 5365,
    "favorites": 31,
    "colors": [
      "#cccccc",
      "#ffffff",
      "#663300",
      "#e7d8b1",
      "#ffcc33"
    ],
    "tags": [],
    "source": "random_fill"
  },
  {
    "id": "139zjw",
    "url": "https://w.wallhaven.cc/full/13/wallhaven-139zjw.png",
    "resolution": "1920x1080",
    "ratio": "1.78",
    "views": 4837,
    "favorites": 79,
    "colors": [
      "#abbcda",
      "#ffffff",
      "#333399",
      "#424153",
      "#66cccc"
    ],
    "tags": [],
    "source": "random_fill"
  },
  {
    "id": "76qlpe",
    "url": "https://w.wallhaven.cc/full/76/wallhaven-76qlpe.jpg",
    "resolution": "3840x2400",
    "ratio": "1.6",
    "views": 6212,
    "favorites": 42,
    "colors": [
      "#424153",
      "#999999",
      "#000000",
      "#cccccc",
      "#e7d8b1"
    ],
    "tags": [],
    "source": "random_fill"
  },
  {
    "id": "4oj2jm",
    "url": "https://w.wallhaven.cc/full/4o/wallhaven-4oj2jm.jpg",
    "resolution": "1920x1200",
    "ratio": "1.6",
    "views": 3368,
    "favorites": 13,
    "colors": [
      "#cccccc",
      "#999999",
      "#ffffff",
      "#abbcda",
      "#663399"
    ],
    "tags": [],
    "source": "random_fill"
  },
  {
    "id": "j3px8q",
    "url": "https://w.wallhaven.cc/full/j3/wallhaven-j3px8q.jpg",
    "resolution": "2560x1440",
    "ratio": "1.78",
    "views": 1283,
    "favorites": 2,
    "colors": [
      "#abbcda",
      "#ffffff",
      "#fdadc7",
      "#cccccc",
      "#ea4c88"
    ],
    "tags": [],
    "source": "random_fill"
  },
  {
    "id": "gjpw6l",
    "url": "https://w.wallhaven.cc/full/gj/wallhaven-gjpw6l.png",
    "resolution": "1920x1080",
    "ratio": "1.78",
    "views": 1924,
    "favorites": 2,
    "colors": [
      "#000000",
      "#424153",
      "#ffffff",
      "#333399",
      "#cccccc"
    ],
    "tags": [],
    "source": "random_fill"
  },
  {
    "id": "4ldj9q",
    "url": "https://w.wallhaven.cc/full/4l/wallhaven-4ldj9q.jpg",
    "resolution": "2560x1600",
    "ratio": "1.6",
    "views": 4123,
    "favorites": 10,
    "colors": [
      "#000000",
      "#0066cc",
      "#0099cc",
      "#333399",
      "#424153"
    ],
    "tags": [],
    "source": "random_fill"
  },
  {
    "id": "x1koll",
    "url": "https://w.wallhaven.cc/full/x1/wallhaven-x1koll.png",
    "resolution": "1920x1080",
    "ratio": "1.78",
    "views": 2138,
    "favorites": 1,
    "colors": [
      "#000000",
      "#999999",
      "#e7d8b1",
      "#424153",
      "#996633"
    ],
    "tags": [],
    "source": "random_fill"
  },
  {
    "id": "3zykp9",
    "url": "https://w.wallhaven.cc/full/3z/wallhaven-3zykp9.jpg",
    "resolution": "2048x1152",
    "ratio": "1.78",
    "views": 13995,
    "favorites": 209,
    "colors": [
      "#424153",
      "#000000",
      "#999999",
      "#996633",
      "#663300"
    ],
    "tags": [],
    "source": "random_fill"
  },
  {
    "id": "4g8owd",
    "url": "https://w.wallhaven.cc/full/4g/wallhaven-4g8owd.jpg",
    "resolution": "1920x1200",
    "ratio": "1.6",
    "views": 3304,
    "favorites": 14,
    "colors": [
      "#424153",
      "#e7d8b1",
      "#0099cc",
      "#333399",
      "#999999"
    ],
    "tags": [],
    "source": "random_fill"
  },
  {
    "id": "1jm8vv",
    "url": "https://w.wallhaven.cc/full/1j/wallhaven-1jm8vv.jpg",
    "resolution": "1920x1080",
    "ratio": "1.78",
    "views": 4822,
    "favorites": 21,
    "colors": [
      "#cccccc",
      "#ffffff",
      "#e7d8b1",
      "#999999",
      "#fdadc7"
    ],
    "tags": [],
    "source": "random_fill"
  },
  {
    "id": "e7y5yr",
    "url": "https://w.wallhaven.cc/full/e7/wallhaven-e7y5yr.jpg",
    "resolution": "2800x1575",
    "ratio": "1.78",
    "views": 2628,
    "favorites": 25,
    "colors": [
      "#424153",
      "#999999",
      "#cccccc",
      "#663399",
      "#ea4c88"
    ],
    "tags": [],
    "source": "random_fill"
  },
  {
    "id": "mpvpey",
    "url": "https://w.wallhaven.cc/full/mp/wallhaven-mpvpey.jpg",
    "resolution": "2560x1440",
    "ratio": "1.78",
    "views": 3782,
    "favorites": 5,
    "colors": [
      "#ffffff",
      "#abbcda",
      "#424153",
      "#cccccc",
      "#999999"
    ],
    "tags": [],
    "source": "random_fill"
  },
  {
    "id": "w832mr",
    "url": "https://w.wallhaven.cc/full/w8/wallhaven-w832mr.jpg",
    "resolution": "2560x1600",
    "ratio": "1.6",
    "views": 2503,
    "favorites": 6,
    "colors": [
      "#999999",
      "#fdadc7",
      "#cccccc",
      "#e7d8b1",
      "#424153"
    ],
    "tags": [],
    "source": "random_fill"
  },
  {
    "id": "mdmeek",
    "url": "https://w.wallhaven.cc/full/md/wallhaven-mdmeek.jpg",
    "resolution": "1920x1080",
    "ratio": "1.78",
    "views": 2176,
    "favorites": 38,
    "colors": [
      "#660000",
      "#000000",
      "#663300",
      "#996633",
      "#424153"
    ],
    "tags": [],
    "source": "random_fill"
  },
  {
    "id": "md2rw1",
    "url": "https://w.wallhaven.cc/full/md/wallhaven-md2rw1.png",
    "resolution": "3840x2160",
    "ratio": "1.78",
    "views": 1647,
    "favorites": 5,
    "colors": [
      "#424153",
      "#999999",
      "#ffffff",
      "#abbcda",
      "#cccccc"
    ],
    "tags": [],
    "source": "random_fill"
  },
  {
    "id": "oxxm97",
    "url": "https://w.wallhaven.cc/full/ox/wallhaven-oxxm97.png",
    "resolution": "1920x1080",
    "ratio": "1.78",
    "views": 4337,
    "favorites": 39,
    "colors": [
      "#cccccc",
      "#000000",
      "#424153",
      "#999999",
      "#996633"
    ],
    "tags": [],
    "source": "random_fill"
  },
  {
    "id": "nkpvq6",
    "url": "https://w.wallhaven.cc/full/nk/wallhaven-nkpvq6.png",
    "resolution": "2560x1440",
    "ratio": "1.78",
    "views": 8630,
    "favorites": 42,
    "colors": [
      "#424153",
      "#333399",
      "#0099cc",
      "#66cccc",
      "#000000"
    ],
    "tags": [],
    "source": "random_fill"
  },
  {
    "id": "xl7ryd",
    "url": "https://w.wallhaven.cc/full/xl/wallhaven-xl7ryd.png",
    "resolution": "1920x1080",
    "ratio": "1.78",
    "views": 2917,
    "favorites": 25,
    "colors": [
      "#abbcda",
      "#ffffff",
      "#999999",
      "#000000",
      "#663399"
    ],
    "tags": [],
    "source": "random_fill"
  },
  {
    "id": "d882xg",
    "url": "https://w.wallhaven.cc/full/d8/wallhaven-d882xg.png",
    "resolution": "2560x1440",
    "ratio": "1.78",
    "views": 2350,
    "favorites": 24,
    "colors": [
      "#000000",
      "#424153",
      "#999999",
      "#663399",
      "#cccccc"
    ],
    "tags": [],
    "source": "random_fill"
  },
  {
    "id": "7pr7yo",
    "url": "https://w.wallhaven.cc/full/7p/wallhaven-7pr7yo.jpg",
    "resolution": "4000x2250",
    "ratio": "1.78",
    "views": 2240,
    "favorites": 36,
    "colors": [
      "#ffffff",
      "#cccccc",
      "#999999",
      "#fdadc7",
      "#abbcda"
    ],
    "tags": [],
    "source": "random_fill"
  },
  {
    "id": "lqkw5l",
    "url": "https://w.wallhaven.cc/full/lq/wallhaven-lqkw5l.jpg",
    "resolution": "2000x1250",
    "ratio": "1.6",
    "views": 2535,
    "favorites": 18,
    "colors": [
      "#ffffff",
      "#cccccc",
      "#000000",
      "#999999",
      "#424153"
    ],
    "tags": [],
    "source": "random_fill"
  },
  {
    "id": "j5mpww",
    "url": "https://w.wallhaven.cc/full/j5/wallhaven-j5mpww.png",
    "resolution": "1920x1080",
    "ratio": "1.78",
    "views": 3972,
    "favorites": 14,
    "colors": [
      "#abbcda",
      "#999999",
      "#cccccc",
      "#424153",
      "#ffffff"
    ],
    "tags": [],
    "source": "random_fill"
  },
  {
    "id": "0pzpge",
    "url": "https://w.wallhaven.cc/full/0p/wallhaven-0pzpge.png",
    "resolution": "1920x1080",
    "ratio": "1.78",
    "views": 5533,
    "favorites": 43,
    "colors": [
      "#999999",
      "#ffffff",
      "#424153",
      "#996633",
      "#cccccc"
    ],
    "tags": [],
    "source": "random_fill"
  },
  {
    "id": "g77o7q",
    "url": "https://w.wallhaven.cc/full/g7/wallhaven-g77o7q.jpg",
    "resolution": "1920x1080",
    "ratio": "1.78",
    "views": 2580,
    "favorites": 20,
    "colors": [
      "#000000",
      "#424153",
      "#999999",
      "#663399",
      "#cccccc"
    ],
    "tags": [],
    "source": "random_fill"
  },
  {
    "id": "d5pr2o",
    "url": "https://w.wallhaven.cc/full/d5/wallhaven-d5pr2o.png",
    "resolution": "2100x1180",
    "ratio": "1.78",
    "views": 3794,
    "favorites": 26,
    "colors": [
      "#424153",
      "#999999",
      "#000000",
      "#996633",
      "#cccccc"
    ],
    "tags": [],
    "source": "random_fill"
  },
  {
    "id": "48lqdy",
    "url": "https://w.wallhaven.cc/full/48/wallhaven-48lqdy.png",
    "resolution": "1920x1080",
    "ratio": "1.78",
    "views": 2835,
    "favorites": 4,
    "colors": [
      "#663300",
      "#424153",
      "#996633",
      "#000000",
      "#660000"
    ],
    "tags": [],
    "source": "random_fill"
  },
  {
    "id": "yjr3kk",
    "url": "https://w.wallhaven.cc/full/yj/wallhaven-yjr3kk.png",
    "resolution": "3840x2160",
    "ratio": "1.78",
    "views": 8456,
    "favorites": 49,
    "colors": [
      "#424153",
      "#333399",
      "#000000",
      "#66cccc",
      "#663399"
    ],
    "tags": [],
    "source": "random_fill"
  },
  {
    "id": "yjm1ld",
    "url": "https://w.wallhaven.cc/full/yj/wallhaven-yjm1ld.jpg",
    "resolution": "2560x1440",
    "ratio": "1.78",
    "views": 44626,
    "favorites": 216,
    "colors": [
      "#000000",
      "#e7d8b1",
      "#424153",
      "#ffffff",
      "#ffcc33"
    ],
    "tags": [],
    "source": "random_fill"
  },
  {
    "id": "d6wmgo",
    "url": "https://w.wallhaven.cc/full/d6/wallhaven-d6wmgo.png",
    "resolution": "2560x1440",
    "ratio": "1.78",
    "views": 3923,
    "favorites": 27,
    "colors": [
      "#424153",
      "#999999",
      "#abbcda",
      "#cccccc",
      "#000000"
    ],
    "tags": [],
    "source": "random_fill"
  },
  {
    "id": "43e7mv",
    "url": "https://w.wallhaven.cc/full/43/wallhaven-43e7mv.jpg",
    "resolution": "1920x1080",
    "ratio": "1.78",
    "views": 5729,
    "favorites": 27,
    "colors": [
      "#333399",
      "#424153",
      "#e7d8b1",
      "#663399",
      "#abbcda"
    ],
    "tags": [],
    "source": "random_fill"
  },
  {
    "id": "8xyl7k",
    "url": "https://w.wallhaven.cc/full/8x/wallhaven-8xyl7k.png",
    "resolution": "1920x1080",
    "ratio": "1.78",
    "views": 3639,
    "favorites": 18,
    "colors": [
      "#999999",
      "#cccccc",
      "#fdadc7",
      "#ffffff",
      "#663399"
    ],
    "tags": [],
    "source": "random_fill"
  },
  {
    "id": "qzq1gl",
    "url": "https://w.wallhaven.cc/full/qz/wallhaven-qzq1gl.png",
    "resolution": "3840x2400",
    "ratio": "1.6",
    "views": 721,
    "favorites": 0,
    "colors": [
      "#000000",
      "#424153",
      "#660000",
      "#996633",
      "#663300"
    ],
    "tags": [],
    "source": "random_fill"
  },
  {
    "id": "76v3vo",
    "url": "https://w.wallhaven.cc/full/76/wallhaven-76v3vo.png",
    "resolution": "1920x1080",
    "ratio": "1.78",
    "views": 7452,
    "favorites": 42,
    "colors": [
      "#424153",
      "#663399",
      "#999999",
      "#ffffff",
      "#abbcda"
    ],
    "tags": [],
    "source": "random_fill"
  },
  {
    "id": "vg9m2p",
    "url": "https://w.wallhaven.cc/full/vg/wallhaven-vg9m2p.jpg",
    "resolution": "1920x1080",
    "ratio": "1.78",
    "views": 1468,
    "favorites": 2,
    "colors": [
      "#ffffff",
      "#cccccc",
      "#424153",
      "#999999",
      "#e7d8b1"
    ],
    "tags": [],
    "source": "random_fill"
  },
  {
    "id": "01dgqw",
    "url": "https://w.wallhaven.cc/full/01/wallhaven-01dgqw.jpg",
    "resolution": "1920x1080",
    "ratio": "1.78",
    "views": 3691,
    "favorites": 18,
    "colors": [
      "#999999",
      "#e7d8b1",
      "#cccccc",
      "#ffffff",
      "#cccc33"
    ],
    "tags": [],
    "source": "random_fill"
  },
  {
    "id": "0jv3wy",
    "url": "https://w.wallhaven.cc/full/0j/wallhaven-0jv3wy.png",
    "resolution": "1920x1080",
    "ratio": "1.78",
    "views": 4669,
    "favorites": 19,
    "colors": [
      "#fdadc7",
      "#e7d8b1",
      "#ffffff",
      "#cccccc",
      "#999999"
    ],
    "tags": [],
    "source": "random_fill"
  },
  {
    "id": "ym7xv7",
    "url": "https://w.wallhaven.cc/full/ym/wallhaven-ym7xv7.png",
    "resolution": "1920x1080",
    "ratio": "1.78",
    "views": 2106,
    "favorites": 25,
    "colors": [
      "#cccccc",
      "#e7d8b1",
      "#abbcda",
      "#424153",
      "#999999"
    ],
    "tags": [],
    "source": "random_fill"
  },
  {
    "id": "zmwqyg",
    "url": "https://w.wallhaven.cc/full/zm/wallhaven-zmwqyg.jpg",
    "resolution": "1920x1080",
    "ratio": "1.78",
    "views": 12254,
    "favorites": 208,
    "colors": [
      "#424153",
      "#999999",
      "#cccccc",
      "#e7d8b1",
      "#996633"
    ],
    "tags": [],
    "source": "random_fill"
  },
  {
    "id": "d515ej",
    "url": "https://w.wallhaven.cc/full/d5/wallhaven-d515ej.png",
    "resolution": "1920x1080",
    "ratio": "1.78",
    "views": 4759,
    "favorites": 11,
    "colors": [
      "#999999",
      "#996633",
      "#424153",
      "#e7d8b1",
      "#cc6633"
    ],
    "tags": [],
    "source": "random_fill"
  },
  {
    "id": "3kll23",
    "url": "https://w.wallhaven.cc/full/3k/wallhaven-3kll23.png",
    "resolution": "1920x1080",
    "ratio": "1.78",
    "views": 5108,
    "favorites": 20,
    "colors": [
      "#000000",
      "#424153",
      "#663300",
      "#999999",
      "#996633"
    ],
    "tags": [],
    "source": "random_fill"
  }
]