[
  {
    "id": "vpywgm",
    "url": "https://w.wallhaven.cc/full/vp/wallhaven-vpywgm.jpg",
    "resolution": "1920x1080",
    "ratio": "1.78",
    "views": 11777,
    "favorites": 77,
    "colors": [
      "#000000",
      "#999999",
      "#424153",
      "#cccccc",
      "#abbcda"
    ],
    "tags": [],
    "source": "monthly_top"
  },
  {
    "id": "xejx2l",
    "url": "https://w.wallhaven.cc/full/xe/wallhaven-xejx2l.jpg",
    "resolution": "3840x2160",
    "ratio": "1.78",
    "views": 7174,
    "favorites": 150,
    "colors": [
      "#424153",
      "#999999",
      "#000000",
      "#ffffff",
      "#cccccc"
    ],
    "tags": [],
    "source": "monthly_top"
  },
  {
    "id": "e8wzkw",
    "url": "https://w.wallhaven.cc/full/e8/wallhaven-e8wzkw.png",
    "resolution": "1920x1080",
    "ratio": "1.78",
    "views": 6466,
    "favorites": 120,
    "colors": [
      "#424153",
      "#000000",
      "#996633",
      "#999999",
      "#663300"
    ],
    "tags": [],
    "source": "monthly_top"
  },
  {
    "id": "7jwy3o",
    "url": "https://w.wallhaven.cc/full/7j/wallhaven-7jwy3o.jpg",
    "resolution": "1920x1080",
    "ratio": "1.78",
    "views": 6147,
    "favorites": 107,
    "colors": [
      "#ffffff",
      "#424153",
      "#999999",
      "#cccccc",
      "#000000"
    ],
    "tags": [],
    "source": "monthly_top"
  },
  {
    "id": "lyk5m2",
    "url": "https://w.wallhaven.cc/full/ly/wallhaven-lyk5m2.jpg",
    "resolution": "1920x1080",
    "ratio": "1.78",
    "views": 4680,
    "favorites": 77,
    "colors": [
      "#fdadc7",
      "#e7d8b1",
      "#996633",
      "#424153",
      "#000000"
    ],
    "tags": [],
    "source": "monthly_top"
  },
  {
    "id": "ly238y",
    "url": "https://w.wallhaven.cc/full/ly/wallhaven-ly238y.png",
    "resolution": "1920x1080",
    "ratio": "1.78",
    "views": 4595,
    "favorites": 75,
    "colors": [
      "#424153",
      "#66cccc",
      "#333399",
      "#0066cc",
      "#0099cc"
    ],
    "tags": [],
    "source": "monthly_top"
  },
  {
    "id": "gw9o8d",
    "url": "https://w.wallhaven.cc/full/gw/wallhaven-gw9o8d.jpg",
    "resolution": "1920x1080",
    "ratio": "1.78",
    "views": 4486,
    "favorites": 100,
    "colors": [
      "#e7d8b1",
      "#996633",
      "#424153",
      "#663300",
      "#999999"
    ],
    "tags": [],
    "source": "monthly_top"
  },
  {
    "id": "9o8j2d",
    "url": "https://w.wallhaven.cc/full/9o/wallhaven-9o8j2d.png",
    "resolution": "3840x2160",
    "ratio": "1.78",
    "views": 4323,
    "favorites": 64,
    "colors": [
      "#000000",
      "#424153",
      "#660000",
      "#990000",
      "#999999"
    ],
    "tags": [],
    "source": "monthly_top"
  },
  {
    "id": "poj6x9",
    "url": "https://w.wallhaven.cc/full/po/wallhaven-poj6x9.jpg",
    "resolution": "4096x2304",
    "ratio": "1.78",
    "views": 4231,
    "favorites": 92,
    "colors": [
      "#424153",
      "#000000",
      "#999999",
      "#cccccc",
      "#ffffff"
    ],
    "tags": [],
    "source": "monthly_top"
  },
  {
    "id": "jekm5y",
    "url": "https://w.wallhaven.cc/full/je/wallhaven-jekm5y.jpg",
    "resolution": "1920x1080",
    "ratio": "1.78",
    "views": 4093,
    "favorites": 86,
    "colors": [
      "#ffffff",
      "#424153",
      "#cccccc",
      "#abbcda",
      "#e7d8b1"
    ],
    "tags": [],
    "source": "monthly_top"
  },
  {
    "id": "oglzx7",
    "url": "https://w.wallhaven.cc/full/og/wallhaven-oglzx7.jpg",
    "resolution": "1920x1080",
    "ratio": "1.78",
    "views": 3770,
    "favorites": 61,
    "colors": [
      "#ffffff",
      "#424153",
      "#cccccc",
      "#999999",
      "#000000"
    ],
    "tags": [],
    "source": "monthly_top"
  },
  {
    "id": "7jr6my",
    "url": "https://w.wallhaven.cc/full/7j/wallhaven-7jr6my.jpg",
    "resolution": "2100x1181",
    "ratio": "1.78",
    "views": 3760,
    "favorites": 59,
    "colors": [
      "#424153",
      "#999999",
      "#ffffff",
      "#cccccc",
      "#996633"
    ],
    "tags": [],
    "source": "monthly_top"
  },
  {
    "id": "ly2mzy",
    "url": "https://w.wallhaven.cc/full/ly/wallhaven-ly2mzy.jpg",
    "resolution": "4096x2304",
    "ratio": "1.78",
    "views": 3618,
    "favorites": 64,
    "colors": [
      "#999999",
      "#424153",
      "#cccccc",
      "#e7d8b1",
      "#ffffff"
    ],
    "tags": [],
    "source": "monthly_top"
  },
  {
    "id": "w5lpm6",
    "url": "https://w.wallhaven.cc/full/w5/wallhaven-w5lpm6.png",
    "resolution": "2560x1440",
    "ratio": "1.78",
    "views": 3483,
    "favorites": 56,
    "colors": [
      "#424153",
      "#333399",
      "#0066cc",
      "#000000",
      "#0099cc"
    ],
    "tags": [],
    "source": "monthly_top"
  },
  {
    "id": "5yrdg7",
    "url": "https://w.wallhaven.cc/full/5y/wallhaven-5yrdg7.jpg",
    "resolution": "4096x2304",
    "ratio": "1.78",
    "views": 3209,
    "favorites": 82,
    "colors": [
      "#cccccc",
      "#999999",
      "#424153",
      "#ffffff",
      "#abbcda"
    ],
    "tags": [],
    "source": "monthly_top"
  },
  {
    "id": "vpyw1l",
    "url": "https://w.wallhaven.cc/full/vp/wallhaven-vpyw1l.jpg",
    "resolution": "7000x3937",
    "ratio": "1.78",
    "views": 3080,
    "favorites": 41,
    "colors": [
      "#000000",
      "#424153",
      "#999999",
      "#abbcda",
      "#663399"
    ],
    "tags": [],
    "source": "monthly_top"
  },
  {
    "id": "w5mew6",
    "url": "https://w.wallhaven.cc/full/w5/wallhaven-w5mew6.jpg",
    "resolution": "3840x2160",
    "ratio": "1.78",
    "views": 3062,
    "favorites": 25,
    "colors": [
      "#000000",
      "#424153",
      "#999999",
      "#cccccc",
      "#ffffff"
    ],
    "tags": [],
    "source": "monthly_top"
  },
  {
    "id": "8gd2oy",
    "url": "https://w.wallhaven.cc/full/8g/wallhaven-8gd2oy.png",
    "resolution": "3840x2160",
    "ratio": "1.78",
    "views": 2852,
    "favorites": 48,
    "colors": [
      "#424153",
      "#ffffff",
      "#66cccc",
      "#77cc33",
      "#999999"
    ],
    "tags": [],
    "source": "monthly_top"
  },
  {
    "id": "k8kmo6",
    "url": "https://w.wallhaven.cc/full/k8/wallhaven-k8kmo6.png",
    "resolution": "3840x2160",
    "ratio": "1.78",
    "views": 2834,
    "favorites": 38,
    "colors": [
      "#424153",
      "#cc3333",
      "#cccccc",
      "#999999",
      "#000000"
    ],
    "tags": [],
    "source": "monthly_top"
  },
  {
    "id": "3q5xjv",
    "url": "https://w.wallhaven.cc/full/3q/wallhaven-3q5xjv.jpg",
    "resolution": "4096x2304",
    "ratio": "1.78",
    "views": 2684,
    "favorites": 33,
    "colors": [
      "#663399",
      "#424153",
      "#abbcda",
      "#999999",
      "#cccccc"
    ],
    "tags": [],
    "source": "monthly_top"
  },
  {
    "id": "213kw6",
    "url": "https://w.wallhaven.cc/full/21/wallhaven-213kw6.jpg",
    "resolution": "3163x1779",
    "ratio": "1.78",
    "views": 2618,
    "favorites": 40,
    "colors": [
      "#000000",
      "#424153",
      "#996633",
      "#999999",
      "#663399"
    ],
    "tags": [],
    "source": "monthly_top"
  },
  {
    "id": "219p39",
    "url": "https://w.wallhaven.cc/full/21/wallhaven-219p39.png",
    "resolution": "2560x1440",
    "ratio": "1.78",
    "views": 2606,
    "favorites": 12,
    "colors": [
      "#424153",
      "#333399",
      "#0099cc",
      "#0066cc",
      "#000000"
    ],
    "tags": [],
    "source": "monthly_top"
  },
  {
    "id": "w5m5xq",
    "url": "https://w.wallhaven.cc/full/w5/wallhaven-w5m5xq.png",
    "resolution": "2205x1240",
    "ratio": "1.78",
    "views": 2586,
    "favorites": 33,
    "colors": [
      "#000000",
      "#ffffff",
      "#424153",
      "#e7d8b1",
      "#999999"
    ],
    "tags": [],
    "source": "monthly_top"
  },
  {
    "id": "lyk5gp",
    "url": "https://w.wallhaven.cc/full/ly/wallhaven-lyk5gp.jpg",
    "resolution": "4096x2304",
    "ratio": "1.78",
    "views": 2588,
    "favorites": 37,
    "colors": [
      "#424153",
      "#663399",
      "#000000",
      "#999999",
      "#abbcda"
    ],
    "tags": [],
    "source": "monthly_top"
  },
  {
    "id": "xe5ovz",
    "url": "https://w.wallhaven.cc/full/xe/wallhaven-xe5ovz.png",
    "resolution": "1920x1080",
    "ratio": "1.78",
    "views": 2410,
    "favorites": 14,
    "colors": [
      "#999999",
      "#cccccc",
      "#424153",
      "#000000",
      "#abbcda"
    ],
    "tags": [],
    "source": "random_fill"
  },
  {
    "id": "r77mpq",
    "url": "https://w.wallhaven.cc/full/r7/wallhaven-r77mpq.png",
    "resolution": "2048x1152",
    "ratio": "1.78",
    "views": 2789,
    "favorites": 34,
    "colors": [
      "#999999",
      "#cccccc",
      "#424153",
      "#660000",
      "#abbcda"
    ],
    "tags": [],
    "source": "random_fill"
  },
  {
    "id": "727599",
    "url": "https://w.wallhaven.cc/full/72/wallhaven-727599.jpg",
    "resolution": "3840x2160",
    "ratio": "1.78",
    "views": 9763,
    "favorites": 162,
    "colors": [
      "#424153",
      "#999999",
      "#000000",
      "#abbcda",
      "#cccccc"
    ],
    "tags": [],
    "source": "random_fill"
  },
  {
    "id": "oxr9l5",
    "url": "https://w.wallhaven.cc/full/ox/wallhaven-oxr9l5.jpg",
    "resolution": "1920x1080",
    "ratio": "1.78",
    "views": 3574,
    "favorites": 43,
    "colors": [
      "#424153",
      "#999999",
      "#cccccc",
      "#996633",
      "#e7d8b1"
    ],
    "tags": [],
    "source": "random_fill"
  },
  {
    "id": "4yplol",
    "url": "https://w.wallhaven.cc/full/4y/wallhaven-4yplol.jpg",
    "resolution": "1920x1080",
    "ratio": "1.78",
    "views": 5240,
    "favorites": 36,
    "colors": [
      "#66cccc",
      "#333399",
      "#0066cc",
      "#0099cc",
      "#424153"
    ],
    "tags": [],
    "source": "random_fill"
  },
  {
    "id": "5769g8",
    "url": "https://w.wallhaven.cc/full/57/wallhaven-5769g8.jpg",
    "resolution": "1920x1200",
    "ratio": "1.6",
    "views": 4587,
    "favorites": 8,
    "colors": [
      "#996633",
      "#cc3333",
      "#ffcc33",
      "#e7d8b1",
      "#ffffff"
    ],
    "tags": [],
    "source": "random_fill"
  },
  {
    "id": "dg6kr3",
    "url": "https://w.wallhaven.cc/full/dg/wallhaven-dg6kr3.jpg",
    "resolution": "3592x2020",
    "ratio": "1.78",
    "views": 1943,
    "favorites": 8,
    "colors": [
      "#424153",
      "#e7d8b1",
      "#999999",
      "#996633",
      "#ffffff"
    ],
    "tags": [],
    "source": "random_fill"
  },
  {
    "id": "4958x8",
    "url": "https://w.wallhaven.cc/full/49/wallhaven-4958x8.png",
    "resolution": "1920x1080",
    "ratio": "1.78",
    "views": 5162,
    "favorites": 36,
    "colors": [
      "#000000",
      "#424153",
      "#999999",
      "#cccccc",
      "#abbcda"
    ],
    "tags": [],
    "source": "random_fill"
  },
  {
    "id": "47lwpe",
    "url": "https://w.wallhaven.cc/full/47/wallhaven-47lwpe.jpg",
    "resolution": "1920x1200",
    "ratio": "1.6",
    "views": 3300,
    "favorites": 8,
    "colors": [
      "#000000",
      "#424153",
      "#cccccc",
      "#999999",
      "#ffffff"
    ],
    "tags": [],
    "source": "random_fill"
  },
  {
    "id": "z8wv1v",
    "url": "https://w.wallhaven.cc/full/z8/wallhaven-z8wv1v.png",
    "resolution": "1923x1080",
    "ratio": "1.78",
    "views": 1392,
    "favorites": 14,
    "colors": [
      "#000000",
      "#424153",
      "#cccccc",
      "#999999",
      "#cc3333"
    ],
    "tags": [],
    "source": "random_fill"
  },
  {
    "id": "d5y593",
    "url": "https://w.wallhaven.cc/full/d5/wallhaven-d5y593.png",
    "resolution": "1920x1080",
    "ratio": "1.78",
    "views": 8122,
    "favorites": 8,
    "colors": [
      "#424153",
      "#999999",
      "#663399",
      "#cccccc",
      "#996633"
    ],
    "tags": [],
    "source": "random_fill"
  },
  {
    "id": "y8yprk",
    "url": "https://w.wallhaven.cc/full/y8/wallhaven-y8yprk.jpg",
    "resolution": "6000x3375",
    "ratio": "1.78",
    "views": 9144,
    "favorites": 54,
    "colors": [
      "#e7d8b1",
      "#999999",
      "#cccccc",
      "#424153",
      "#ffffff"
    ],
    "tags": [],
    "source": "random_fill"
  },
  {
    "id": "6kxzd7",
    "url": "https://w.wallhaven.cc/full/6k/wallhaven-6kxzd7.jpg",
    "resolution": "1920x1080",
    "ratio": "1.78",
    "views": 2390,
    "favorites": 15,
    "colors": [
      "#333399",
      "#663399",
      "#993399",
      "#424153",
      "#fdadc7"
    ],
    "tags": [],
    "source": "random_fill"
  },
  {
    "id": "e7pwdw",
    "url": "https://w.wallhaven.cc/full/e7/wallhaven-e7pwdw.jpg",
    "resolution": "5000x2812",
    "ratio": "1.78",
    "views": 152447,
    "favorites": 2017,
    "colors": [
      "#663300",
      "#996633",
      "#e7d8b1",
      "#000000",
      "#999999"
    ],
    "tags": [],
    "source": "random_fill"
  },
  {
    "id": "1jgrqv",
    "url": "https://w.wallhaven.cc/full/1j/wallhaven-1jgrqv.png",
    "resolution": "1920x1080",
    "ratio": "1.78",
    "views": 2075,
    "favorites": 3,
    "colors": [
      "#cccccc",
      "#ffffff",
      "#abbcda",
      "#999999",
      "#e7d8b1"
    ],
    "tags": [],
    "source": "random_fill"
  },
  {
    "id": "gjm1ll",
    "url": "https://w.wallhaven.cc/full/gj/wallhaven-gjm1ll.png",
    "resolution": "2268x1276",
    "ratio": "1.78",
    "views": 2621,
    "favorites": 25,
    "colors": [
      "#ffffff",
      "#cccccc",
      "#abbcda",
      "#999999",
      "#e7d8b1"
    ],
    "tags": [],
    "source": "random_fill"
  },
  {
    "id": "47pzwy",
    "url": "https://w.wallhaven.cc/full/47/wallhaven-47pzwy.jpg",
    "resolution": "1920x1080",
    "ratio": "1.78",
    "views": 18899,
    "favorites": 56,
    "colors": [
      "#000000",
      "#424153",
      "#333399",
      "#0066cc",
      "#66cccc"
    ],
    "tags": [],
    "source": "random_fill"
  },
  {
    "id": "w8gw9r",
    "url": "https://w.wallhaven.cc/full/w8/wallhaven-w8gw9r.jpg",
    "resolution": "1920x1200",
    "ratio": "1.6",
    "views": 2639,
    "favorites": 10,
    "colors": [
      "#424153",
      "#000000",
      "#ffffff",
      "#996633",
      "#e7d8b1"
    ],
    "tags": [],
    "source": "random_fill"
  },
  {
    "id": "zxvl6j",
    "url": "https://w.wallhaven.cc/full/zx/wallhaven-zxvl6j.png",
    "resolution": "1920x1200",
    "ratio": "1.6",
    "views": 4455,
    "favorites": 11,
    "colors": [
      "#ffffff",
      "#999999",
      "#abbcda",
      "#663399",
      "#cccccc"
    ],
    "tags": [],
    "source": "random_fill"
  },
  {
    "id": "odvzel",
    "url": "https://w.wallhaven.cc/full/od/wallhaven-odvzel.jpg",
    "resolution": "1920x1080",
    "ratio": "1.78",
    "views": 5931,
    "favorites": 20,
    "colors": [
      "#000000",
      "#424153",
      "#999999",
      "#996633",
      "#660000"
    ],
    "tags": [],
    "source": "random_fill"
  },
  {
    "id": "lqwo8p",
    "url": "https://w.wallhaven.cc/full/lq/wallhaven-lqwo8p.png",
    "resolution": "1920x1200",
    "ratio": "1.6",
    "views": 6214,
    "favorites": 9,
    "colors": [
      "#424153",
      "#66cccc",
      "#999999",
      "#0099cc",
      "#ffffff"
    ],
    "tags": [],
    "source": "random_fill"
  },
  {
    "id": "k9w271",
    "url": "https://w.wallhaven.cc/full/k9/wallhaven-k9w271.jpg",
    "resolution": "1920x1080",
    "ratio": "1.78",
    "views": 1509,
    "favorites": 4,
    "colors": [
      "#660000",
      "#000000",
      "#990000",
      "#cc6633",
      "#663300"
    ],
    "tags": [],
    "source": "random_fill"
  },
  {
    "id": "96mqpk",
    "url": "https://w.wallhaven.cc/full/96/wallhaven-96mqpk.jpg",
    "resolution": "1920x1200",
    "ratio": "1.6",
    "views": 3453,
    "favorites": 33,
    "colors": [
      "#e7d8b1",
      "#424153",
      "#ea4c88",
      "#999999",
      "#996633"
    ],
    "tags": [],
    "source": "random_fill"
  },
  {
    "id": "2ywzrm",
    "url": "https://w.wallhaven.cc/full/2y/wallhaven-2ywzrm.png",
    "resolution": "3840x2160",
    "ratio": "1.78",
    "views": 3987,
    "favorites": 45,
    "colors": [
      "#000000",
      "#424153",
      "#999999",
      "#cccccc",
      "#660000"
    ],
    "tags": [],
    "source": "random_fill"
  },
  {
    "id": "rrpvkm",
    "url": "https://w.wallhaven.cc/full/rr/wallhaven-rrpvkm.png",
    "resolution": "2560x1440",
    "ratio": "1.78",
    "views": 16848,
    "favorites": 141,
    "colors": [
      "#424153",
      "#333399",
      "#66cccc",
      "#abbcda",
      "#999999"
    ],
    "tags": [],
    "source": "random_fill"
  },
  {
    "id": "6qw95x",
    "url": "https://w.wallhaven.cc/full/6q/wallhaven-6qw95x.png",
    "resolution": "1920x1200",
    "ratio": "1.6",
    "views": 1708,
    "favorites": 0,
    "colors": [
      "#ffffff",
      "#cccccc",
      "#424153",
      "#e7d8b1",
      "#abbcda"
    ],
    "tags": [],
    "source": "random_fill"
  },
  {
    "id": "399986",
    "url": "https://w.wallhaven.cc/full/39/wallhaven-399986.png",
    "resolution": "1920x1080",
    "ratio": "1.78",
    "views": 2504,
    "favorites": 19,
    "colors": [
      "#663399",
      "#424153",
      "#ffcc33",
      "#e7d8b1",
      "#996633"
    ],
    "tags": [],
    "source": "random_fill"
  },
  {
    "id": "p2rj6p",
    "url": "https://w.wallhaven.cc/full/p2/wallhaven-p2rj6p.png",
    "resolution": "1920x1080",
    "ratio": "1.78",
    "views": 2898,
    "favorites": 27,
    "colors": [
      "#999999",
      "#cccccc",
      "#424153",
      "#996633",
      "#abbcda"
    ],
    "tags": [],
    "source": "random_fill"
  },
  {
    "id": "j8ywvq",
    "url": "https://w.wallhaven.cc/full/j8/wallhaven-j8ywvq.jpg",
    "resolution": "1920x1080",
    "ratio": "1.78",
    "views": 4861,
    "favorites": 14,
    "colors": [
      "#ffffff",
      "#000000",
      "#999999",
      "#cccccc",
      "#cc0000"
    ],
    "tags": [],
    "source": "random_fill"
  },
  {
    "id": "85qdjo",
    "url": "https://w.wallhaven.cc/full/85/wallhaven-85qdjo.png",
    "resolution": "2559x1439",
    "ratio": "1.78",
    "views": 2482,
    "favorites": 21,
    "colors": [
      "#424153",
      "#abbcda",
      "#000000",
      "#999999",
      "#660000"
    ],
    "tags": [],
    "source": "random_fill"
  },
  {
    "id": "5w9e85",
    "url": "https://w.wallhaven.cc/full/5w/wallhaven-5w9e85.jpg",
    "resolution": "1920x1080",
    "ratio": "1.78",
    "views": 3716,
    "favorites": 52,
    "colors": [
      "#ffcc33",
      "#424153",
      "#cccccc",
      "#000000",
      "#999999"
    ],
    "tags": [],
    "source": "random_fill"
  },
  {
    "id": "lm9zp2",
    "url": "https://w.wallhaven.cc/full/lm/wallhaven-lm9zp2.png",
    "resolution": "1920x1080",
    "ratio": "1.78",
    "views": 1665,
    "favorites": 4,
    "colors": [
      "#336600",
      "#424153",
      "#666600",
      "#669900",
      "#77cc33"
    ],
    "tags": [],
    "source": "random_fill"
  },
  {
    "id": "p2ye8e",
    "url": "https://w.wallhaven.cc/full/p2/wallhaven-p2ye8e.jpg",
    "resolution": "1920x1080",
    "ratio": "1.78",
    "views": 2189,
    "favorites": 3,
    "colors": [
      "#cccccc",
      "#ffffff",
      "#e7d8b1",
      "#999999",
      "#424153"
    ],
    "tags": [],
    "source": "random_fill"
  },
  {
    "id": "g7l37e",
    "url": "https://w.wallhaven.cc/full/g7/wallhaven-g7l37e.jpg",
    "resolution": "1920x1080",
    "ratio": "1.78",
    "views": 2417,
    "favorites": 12,
    "colors": [
      "#999999",
      "#424153",
      "#e7d8b1",
      "#996633",
      "#cccccc"
    ],
    "tags": [],
    "source": "random_fill"
  },
  {
    "id": "nej2pw",
    "url": "https://w.wallhaven.cc/full/ne/wallhaven-nej2pw.jpg",
    "resolution": "1920x1197",
    "ratio": "1.6",
    "views": 2743,
    "favorites": 27,
    "colors": [
      "#424153",
      "#999999",
      "#000000",
      "#cccccc",
      "#ffffff"
    ],
    "tags": [],
    "source": "random_fill"
  },
  {
    "id": "nzp83g",
    "url": "https://w.wallhaven.cc/full/nz/wallhaven-nzp83g.jpg",
    "resolution": "1920x1080",
    "ratio": "1.78",
    "views": 4059,
    "favorites": 14,
    "colors": [
      "#ffffff",
      "#cccccc",
      "#424153",
      "#999999",
      "#abbcda"
    ],
    "tags": [],
    "source": "random_fill"
  },
  {
    "id": "k9x8y1",
    "url": "https://w.wallhaven.cc/full/k9/wallhaven-k9x8y1.png",
    "resolution": "1920x1080",
    "ratio": "1.78",
    "views": 2202,
    "favorites": 1,
    "colors": [
      "#ffffff",
      "#663300",
      "#660000",
      "#000000",
      "#990000"
    ],
    "tags": [],
    "source": "random_fill"
  },
  {
    "id": "k9l96d",
    "url": "https://w.wallhaven.cc/full/k9/wallhaven-k9l96d.jpg",
    "resolution": "1920x1080",
    "ratio": "1.78",
    "views": 1969,
    "favorites": 6,
    "colors": [
      "#e7d8b1",
      "#ffffff",
      "#424153",
      "#999999",
      "#cccccc"
    ],
    "tags": [],
    "source": "random_fill"
  },
  {
    "id": "ne68po",
    "url": "https://w.wallhaven.cc/full/ne/wallhaven-ne68po.jpg",
    "resolution": "1920x1080",
    "ratio": "1.78",
    "views": 2743,
    "favorites": 1,
    "colors": [
      "#e7d8b1",
      "#cccc33",
      "#ffcc33",
      "#ffffff",
      "#cc6633"
    ],
    "tags": [],
    "source": "random_fill"
  },
  {
    "id": "6llp5q",
    "url": "https://w.wallhaven.cc/full/6l/wallhaven-6llp5q.png",
    "resolution": "2560x1440",
    "ratio": "1.78",
    "views": 3075,
    "favorites": 38,
    "colors": [
      "#424153",
      "#000000",
      "#e7d8b1",
      "#996633",
      "#999999"
    ],
    "tags": [],
    "source": "random_fill"
  },
  {
    "id": "d6wemg",
    "url": "https://w.wallhaven.cc/full/d6/wallhaven-d6wemg.png",
    "resolution": "1920x1080",
    "ratio": "1.78",
    "views": 1910,
    "favorites": 8,
    "colors": [
      "#424153",
      "#999999",
      "#000000",
      "#663399",
      "#333399"
    ],
    "tags": [],
    "source": "random_fill"
  },
  {
    "id": "49plxk",
    "url": "https://w.wallhaven.cc/full/49/wallhaven-49plxk.png",
    "resolution": "1920x1080",
    "ratio": "1.78",
    "views": 3324,
    "favorites": 11,
    "colors": [
      "#996633",
      "#ffcc33",
      "#424153",
      "#e7d8b1",
      "#cccc33"
    ],
    "tags": [],
    "source": "random_fill"
  },
  {
    "id": "4dgodj",
    "url": "https://w.wallhaven.cc/full/4d/wallhaven-4dgodj.jpg",
    "resolution": "1920x1200",
    "ratio": "1.6",
    "views": 3911,
    "favorites": 24,
    "colors": [
      "#000000",
      "#ffffff",
      "#cccccc",
      "#660000",
      "#424153"
    ],
    "tags": [],
    "source": "random_fill"
  },
  {
    "id": "83mq5k",
    "url": "https://w.wallhaven.cc/full/83/wallhaven-83mq5k.png",
    "resolution": "2560x1440",
    "ratio": "1.78",
    "views": 9749,
    "favorites": 11,
    "colors": [
      "#424153",
      "#000000",
      "#999999",
      "#663399",
      "#996633"
    ],
    "tags": [],
    "source": "random_fill"
  },
  {
    "id": "dpk3gj",
    "url": "https://w.wallhaven.cc/full/dp/wallhaven-dpk3gj.jpg",
    "resolution": "3200x2000",
    "ratio": "1.6",
    "views": 4405,
    "favorites": 35,
    "colors": [
      "#424153",
      "#999999",
      "#000000",
      "#cccccc",
      "#996633"
    ],
    "tags": [],
    "source": "random_fill"
  },
  {
    "id": "4816yo",
    "url": "https://w.wallhaven.cc/full/48/wallhaven-4816yo.jpg",
    "resolution": "1920x1080",
    "ratio": "1.78",
    "views": 4708,
    "favorites": 25,
    "colors": [
      "#000000",
      "#424153",
      "#333399",
      "#cc3333",
      "#999999"
    ],
    "tags": [],
    "source": "random_fill"
  },
  {
    "id": "8o8ooy",
    "url": "https://w.wallhaven.cc/full/8o/wallhaven-8o8ooy.jpg",
    "resolution": "2844x1600",
    "ratio": "1.78",
    "views": 7498,
    "favorites": 131,
    "colors": [
      "#424153",
      "#663300",
      "#000000",
      "#996633",
      "#999999"
    ],
    "tags": [],
    "source": "random_fill"
  },
  {
    "id": "j56dwp",
    "url": "https://w.wallhaven.cc/full/j5/wallhaven-j56dwp.png",
    "resolution": "1920x1080",
    "ratio": "1.78",
    "views": 2903,
    "favorites": 27,
    "colors": [
      "#424153",
      "#999999",
      "#000000",
      "#993399",
      "#cccccc"
    ],
    "tags": [],
    "source": "random_fill"
  },
  {
    "id": "73wj69",
    "url": "https://w.wallhaven.cc/full/73/wallhaven-73wj69.jpg",
    "resolution": "1920x1080",
    "ratio": "1.78",
    "views": 1676,
    "favorites": 16,
    "colors": [
      "#999999",
      "#424153",
      "#abbcda",
      "#66cccc",
      "#cccccc"
    ],
    "tags": [],
    "source": "random_fill"
  },
  {
    "id": "43pgmd",
    "url": "https://w.wallhaven.cc/full/43/wallhaven-43pgmd.png",
    "resolution": "3840x2160",
    "ratio": "1.78",
    "views": 3216,
    "favorites": 17,
    "colors": [
      "#e7d8b1",
      "#999999",
      "#663300",
      "#996633",
      "#000000"
    ],
    "tags": [],
    "source": "random_fill"
  },
  {
    "id": "7pv1ry",
    "url": "https://w.wallhaven.cc/full/7p/wallhaven-7pv1ry.png",
    "resolution": "2560x1440",
    "ratio": "1.78",
    "views": 4211,
    "favorites": 15,
    "colors": [
      "#424153",
      "#000000",
      "#333399",
      "#0066cc",
      "#999999"
    ],
    "tags": [],
    "source": "random_fill"
  },
  {
    "id": "6qoxm6",
    "url": "https://w.wallhaven.cc/full/6q/wallhaven-6qoxm6.jpg",
    "resolution": "1920x1080",
    "ratio": "1.78",
    "views": 1577,
    "favorites": 3,
    "colors": [
      "#ffffff",
      "#e7d8b1",
      "#ffcc33",
      "#cccccc",
      "#cccc33"
    ],
    "tags": [],
    "source": "random_fill"
  },
  {
    "id": "lmrw9q",
    "url": "https://w.wallhaven.cc/full/lm/wallhaven-lmrw9q.jpg",
    "resolution": "1920x1080",
    "ratio": "1.78",
    "views": 1770,
    "favorites": 1,
    "colors": [
      "#abbcda",
      "#66cccc",
      "#ffffff",
      "#333399",
      "#424153"
    ],
    "tags": [],
    "source": "random_fill"
  },
  {
    "id": "r2q9pj",
    "url": "https://w.wallhaven.cc/full/r2/wallhaven-r2q9pj.png",
    "resolution": "7680x4320",
    "ratio": "1.78",
    "views": 2171,
    "favorites": 4,
    "colors": [
      "#e7d8b1",
      "#cccc33",
      "#996633",
      "#999900",
      "#999999"
    ],
    "tags": [],
    "source": "random_fill"
  },
  {
    "id": "ym5led",
    "url": "https://w.wallhaven.cc/full/ym/wallhaven-ym5led.png",
    "resolution": "3428x1928",
    "ratio": "1.78",
    "views": 13586,
    "favorites": 163,
    "colors": [
      "#ffffff",
      "#fdadc7",
      "#cccccc",
      "#ea4c88",
      "#000000"
    ],
    "tags": [],
    "source": "random_fill"
  },
  {
    "id": "qzegpd",
    "url": "https://w.wallhaven.cc/full/qz/wallhaven-qzegpd.png",
    "resolution": "3840x2160",
    "ratio": "1.78",
    "views": 4244,
    "favorites": 53,
    "colors": [
      "#abbcda",
      "#fdadc7",
      "#66cccc",
      "#cc3333",
      "#663399"
    ],
    "tags": [],
    "source": "random_fill"
  },
  {
    "id": "nzyxvg",
    "url": "https://w.wallhaven.cc/full/nz/wallhaven-nzyxvg.png",
    "resolution": "1920x1080",
    "ratio": "1.78",
    "views": 5353,
    "favorites": 27,
    "colors": [
      "#999999",
      "#424153",
      "#996633",
      "#e7d8b1",
      "#ffffff"
    ],
    "tags": [],
    "source": "random_fill"
  },
  {
    "id": "g8gemq",
    "url": "https://w.wallhaven.cc/full/g8/wallhaven-g8gemq.jpg",
    "resolution": "3242x1824",
    "ratio": "1.78",
    "views": 5217,
    "favorites": 13,
    "colors": [
      "#424153",
      "#999999",
      "#996633",
      "#000000",
      "#e7d8b1"
    ],
    "tags": [],
    "source": "random_fill"
  },
  {
    "id": "4g2mwq",
    "url": "https://w.wallhaven.cc/full/4g/wallhaven-4g2mwq.jpg",
    "resolution": "1920x1080",
    "ratio": "1.78",
    "views": 3925,
    "favorites": 8,
    "colors": [
      "#cccccc",
      "#999999",
      "#ea4c88",
      "#424153",
      "#cc3333"
    ],
    "tags": [],
    "source": "random_fill"
  },
  {
    "id": "gp2gyq",
    "url": "https://w.wallhaven.cc/full/gp/wallhaven-gp2gyq.png",
    "resolution": "1920x1080",
    "ratio": "1.78",
    "views": 2948,
    "favorites": 8,
    "colors": [
      "#663300",
      "#996633",
      "#cc6633",
      "#000000",
      "#cc3333"
    ],
    "tags": [],
    "source": "random_fill"
  },
  {
    "id": "w8p21p",
    "url": "https://w.wallhaven.cc/full/w8/wallhaven-w8p21p.jpg",
    "resolution": "3508x2192",
    "ratio": "1.6",
    "views": 4497,
    "favorites": 63,
    "colors": [
      "#424153",
      "#663399",
      "#000000",
      "#999999",
      "#333399"
    ],
    "tags": [],
    "source": "random_fill"
  },
  {
    "id": "1p8871",
    "url": "https://w.wallhaven.cc/full/1p/wallhaven-1p8871.jpg",
    "resolution": "7680x4320",
    "ratio": "1.78",
    "views": 29694,
    "favorites": 168,
    "colors": [
      "#000000",
      "#424153",
      "#66cccc",
      "#abbcda",
      "#333399"
    ],
    "tags": [],
    "source": "random_fill"
  },
  {
    "id": "3z67kv",
    "url": "https://w.wallhaven.cc/full/3z/wallhaven-3z67kv.png",
    "resolution": "1920x1080",
    "ratio": "1.78",
    "views": 1671,
    "favorites": 26,
    "colors": [
      "#424153",
      "#000000",
      "#999999",
      "#ffffff",
      "#cccccc"
    ],
    "tags": [],
    "source": "random_fill"
  },
  {
    "id": "d8xdzj",
    "url": "https://w.wallhaven.cc/full/d8/wallhaven-d8xdzj.png",
    "resolution": "1920x1080",
    "ratio": "1.78",
    "views": 1997,
    "favorites": 17,
    "colors": [
      "#424153",
      "#999999",
      "#cccccc",
      "#000000",
      "#abbcda"
    ],
    "tags": [],
    "source": "random_fill"
  },
  {
    "id": "mdekx8",
    "url": "https://w.wallhaven.cc/full/md/wallhaven-mdekx8.png",
    "resolution": "2880x1800",
    "ratio": "1.6",
    "views": 3879,
    "favorites": 7,
    "colors": [
      "#000000",
      "#424153",
      "#e7d8b1",
      "#999999",
      "#ea4c88"
    ],
    "tags": [],
    "source": "random_fill"
  },
  {
    "id": "nrd2rm",
    "url": "https://w.wallhaven.cc/full/nr/wallhaven-nrd2rm.jpg",
    "resolution": "1920x1080",
    "ratio": "1.78",
    "views": 2511,
    "favorites": 3,
    "colors": [
      "#000000",
      "#cc0000",
      "#660000",
      "#990000",
      "#999999"
    ],
    "tags": [],
    "source": "random_fill"
  },
  {
    "id": "gj7yr7",
    "url": "https://w.wallhaven.cc/full/gj/wallhaven-gj7yr7.png",
    "resolution": "1920x1200",
    "ratio": "1.6",
    "views": 1884,
    "favorites": 4,
    "colors": [
      "#ffffff",
      "#abbcda",
      "#424153",
      "#cccccc",
      "#999999"
    ],
    "tags": [],
    "source": "random_fill"
  },
  {
    "id": "yx81qg",
    "url": "https://w.wallhaven.cc/full/yx/wallhaven-yx81qg.jpg",
    "resolution": "3840x2160",
    "ratio": "1.78",
    "views": 2014,
    "favorites": 36,
    "colors": [
      "#424153",
      "#999999",
      "#333399",
      "#663399",
      "#cccccc"
    ],
    "tags": [],
    "source": "random_fill"
  },
  {
    "id": "vmdzyp",
    "url": "https://w.wallhaven.cc/full/vm/wallhaven-vmdzyp.jpg",
    "resolution": "1920x1080",
    "ratio": "1.78",
    "views": 2298,
    "favorites": 10,
    "colors": [
      "#cccccc",
      "#ffffff",
      "#999999",
      "#424153",
      "#abbcda"
    ],
    "tags": [],
    "source": "random_fill"
  },
  {
    "id": "o38oq7",
    "url": "https://w.wallhaven.cc/full/o3/wallhaven-o38oq7.jpg",
    "resolution": "1920x1080",
    "ratio": "1.78",
    "views": 866,
    "favorites": 1,
    "colors": [
      "#424153",
      "#000000",
      "#ffffff",
      "#993399",
      "#663399"
    ],
    "tags": [],
    "source": "random_fill"
  },
  {
    "id": "ne9l1r",
    "url": "https://w.wallhaven.cc/full/ne/wallhaven-ne9l1r.jpg",
    "resolution": "1920x1080",
    "ratio": "1.78",
    "views": 2125,
    "favorites": 0,
    "colors": [
      "#000000",
      "#cccccc",
      "#ffffff",
      "#424153",
      "#999999"
    ],
    "tags": [],
    "source": "random_fill"
  },
  {
    "id": "nmlqe9",
    "url": "https://w.wallhaven.cc/full/nm/wallhaven-nmlqe9.jpg",
    "resolution": "1920x1200",
    "ratio": "1.6",
    "views": 3039,
    "favorites": 5,
    "colors": [
      "#000000",
      "#424153",
      "#999999",
      "#996633",
      "#663300"
    ],
    "tags": [],
    "source": "random_fill"
  },
  {
    "id": "p9ekxj",
    "url": "https://w.wallhaven.cc/full/p9/wallhaven-p9ekxj.png",
    "resolution": "1920x1080",
    "ratio": "1.78",
    "views": 2048,
    "favorites": 4,
    "colors": [
      "#fdadc7",
      "#e7d8b1",
      "#ffffff",
      "#cccccc",
      "#999999"
    ],
    "tags": [],
    "source": "random_fill"
  },
  {
    "id": "219yoy",
    "url": "https://w.wallhaven.cc/full/21/wallhaven-219yoy.jpg",
    "resolution": "1920x1080",
    "ratio": "1.78",
    "views": 292,
    "favorites": 1,
    "colors": [
      "#424153",
      "#000000",
      "#999999",
      "#cccccc",
      "#660000"
    ],
    "tags": [],
    "source": "random_fill"
  },
  {
    "id": "4dgq8o",
    "url": "https://w.wallhaven.cc/full/4d/wallhaven-4dgq8o.jpg",
    "resolution": "1920x1080",
    "ratio": "1.78",
    "views": 4431,
    "favorites": 31,
    "colors": [
      "#ffffff",
      "#cccccc",
      "#abbcda",
      "#999999",
      "#663399"
    ],
    "tags": [],
    "source": "random_fill"
  },
  {
    "id": "m93gw9",
    "url": "https://w.wallhaven.cc/full/m9/wallhaven-m93gw9.jpg",
    "resolution": "1920x1080",
    "ratio": "1.78",
    "views": 3930,
    "favorites": 12,
    "colors": [
      "#ffffff",
      "#0099cc",
      "#999999",
      "#ffcc33",
      "#66cccc"
    ],
    "tags": [],
    "source": "random_fill"
  }
]